<treebank xmlns:saxon="http://saxon.sf.net/" text_id="24027" format="aldt" version="1.5" direction="ltr" xml:lang="grc">
  <annotator name="Polina Yordanova" address="polina.v.yordanova@gmail.com" role="approved" date="2022-07-18" layer="reg"/>
  <annotator name="Polina Yordanova" address="polina.v.yordanova@gmail.com" role="approved" date="2022-07-18" layer="orig"/>
  <annotator name="Sari Kock" address="kock.sari@gmail.com" role="annotated" date="2021-06-23" layer="orig"/>
  <annotator name="Sari Kock" address="kock.sari@gmail.com" role="annotated" date="2021-06-23" layer="reg"/>
  <annotator name="Petri Lahtinen" address="petri.m.lahtinen@gmail.com" role="annotated (previously)" date="2018-11-05" layer="reg"/>
  <annotator name="Petri Lahtinen" address="petri.m.lahtinen@gmail.com" role="annotated (previously)" date="2018-11-05" layer="orig"/>
  <document_meta name="p.cair.zen.1.59093.xml" series_name="p.cair.zen" series_type="documentary" tm_id="747" hgv_id="747" date_not_before="-257" date_not_after="" place_name="Syrien"/>
  <hand_meta name="m1" id="1">
    <text_type hypercategory="PRIVATE" category="Letter" subcategory=""/>
    <person pg_id="636" tm_id="1879" role="author" handwriting="" honorific_epithet="" ethnic_label="" occupation="" domicile="" age="" education="" name="Herakleitos" gender="1" uncertain=""/>
    <person pg_id="133" tm_id="1757" role="addressee" handwriting="" honorific_epithet="" ethnic_label="" occupation="" domicile="" age="" education="" name="Zenon" gender="1" uncertain=""/>
    <person pg_id="636" tm_id="1879" role="writer" handwriting="" honorific_epithet="" ethnic_label="" occupation="" domicile="" age="" education="" name="Herakleitos" gender="1" uncertain="1"/>
  </hand_meta>
  <sentence id="1">
    <word id="1" form_orig="Ἡράκλειτος" form_reg="Ἡράκλειτος" lemma_orig="Ἡράκλειτος" postag_orig="n-s---mn-" relation_orig="SBJ" head_orig="5" lemma_reg="Ἡράκλειτος" postag_reg="n-s---mn-" relation_reg="SBJ" head_reg="5" tp_n="1" line_n="1" lang="grc" hand_id="1" tm_word_id=""/>
    <word id="2" form_orig="Ζήνωνι" form_reg="Ζήνωνι" lemma_orig="Ζήνων" postag_orig="n-s---md-" relation_orig="OBJ" head_orig="5" lemma_reg="Ζήνων" postag_reg="n-s---md-" relation_reg="OBJ" head_reg="5" tp_n="1" line_n="1" lang="grc" hand_id="2" tm_word_id=""/>
    <word id="3" form_orig="χαίρειν" form_reg="χαίρειν" lemma_orig="χαίρω" postag_orig="v--pna---" relation_orig="OBJ" head_orig="5" lemma_reg="χαίρω" postag_reg="v--pna---" relation_reg="OBJ" head_reg="5" tp_n="1" line_n="1" lang="grc" hand_id="3" tm_word_id=""/>
    <word id="4" form_orig="." form_reg="." lemma_orig="punc1" postag_orig="u--------" relation_orig="AuxK" head_orig="0" lemma_reg="punc1" postag_reg="u--------" relation_reg="AuxK" head_reg="0" tp_n="1" line_n="1" lang="grc" hand_id="4" tm_word_id=""/>
    <word id="5" form_orig="[0]" form_reg="[0]" lemma_orig="" postag_orig="" relation_orig="PRED" head_orig="0" lemma_reg="" postag_reg="" relation_reg="PRED" head_reg="0" insertion_id="0000e" artificial="elliptic" tp_n="" line_n="None" lang="None" hand_id="5" tm_word_id=""/>
  </sentence>
  <sentence id="2">
    <word id="1" form_orig="[εἰ]" form_reg="εἰ" lemma_orig="" postag_orig="" relation_orig="" head_orig="" lemma_reg="εἰ" postag_reg="c--------" relation_reg="AuxC" head_reg="13" tp_n="1" line_n="1" lang="grc" hand_id="6" tm_word_id=""/>
    <word id="2" form_orig="[αὐτός]" form_reg="αὐτός" lemma_orig="" postag_orig="" relation_orig="" head_orig="" lemma_reg="αὐτός" postag_reg="p-s---mn-" relation_reg="SBJ" head_reg="4" tp_n="1" line_n="1" lang="grc" hand_id="7" tm_word_id=""/>
    <word id="3" form_orig="[τε]" form_reg="τε" lemma_orig="" postag_orig="" relation_orig="" head_orig="" lemma_reg="τε" postag_reg="c--------" relation_reg="AuxY" head_reg="5" tp_n="1" line_n="1" lang="grc" hand_id="8" tm_word_id=""/>
    <word id="4" form_orig="[ἔρρ]ωσαι" form_reg="ἔρρωσαι" lemma_orig="" postag_orig="" relation_orig="" head_orig="" lemma_reg="ῥώννυμι" postag_reg="v2srie---" relation_reg="ADV_CO" head_reg="5" tp_n="1" line_n="1" lang="grc" hand_id="9" tm_word_id=""/>
    <word id="5" form_orig="καὶ" form_reg="καὶ" lemma_orig="καί" postag_orig="c--------" relation_orig="" head_orig="" lemma_reg="καί" postag_reg="c--------" relation_reg="COORD" head_reg="1" tp_n="1" line_n="1" lang="grc" hand_id="10" tm_word_id=""/>
    <word id="6" form_orig="τὰ" form_reg="τὰ" lemma_orig="ὁ" postag_orig="l-p---nn-" relation_orig="ATR" head_orig="7" lemma_reg="ὁ" postag_reg="l-p---nn-" relation_reg="ATR" head_reg="7" tp_n="1" line_n="1" lang="grc" hand_id="11" tm_word_id=""/>
    <word id="7" form_orig="λοιπὰ" form_reg="λοιπὰ" lemma_orig="λοιπός" postag_orig="a-p---nn-" relation_orig="SBJ" head_orig="9" lemma_reg="λοιπός" postag_reg="a-p---nn-" relation_reg="SBJ" head_reg="9" tp_n="1" line_n="1" lang="grc" hand_id="12" tm_word_id=""/>
    <word id="8" form_orig="σοί" form_reg="σοί" lemma_orig="σύ" postag_orig="p2s---md-" relation_orig="OBJ" head_orig="9" lemma_reg="σύ" postag_reg="p2s---md-" relation_reg="OBJ" head_reg="9" tp_n="1" line_n="1" lang="grc" hand_id="13" tm_word_id=""/>
    <word id="9" form_orig="ἐστιν" form_reg="ἐστιν" lemma_orig="εἰμί" postag_orig="v3spia---" relation_orig="" head_orig="" lemma_reg="εἰμί" postag_reg="v3spia---" relation_reg="ADV_CO" head_reg="5" tp_n="1" line_n="1" lang="grc" hand_id="14" tm_word_id=""/>
    <word id="10" form_orig="κατὰ" form_reg="κατὰ" lemma_orig="κατά" postag_orig="r--------" relation_orig="AuxP" head_orig="9" lemma_reg="κατά" postag_reg="r--------" relation_reg="AuxP" head_reg="9" tp_n="1" line_n="2" lang="grc" hand_id="15" tm_word_id=""/>
    <word id="11" form_orig="λόγον" form_reg="λόγον" lemma_orig="λόγος" postag_orig="n-s---ma-" relation_orig="ADV" head_orig="10" lemma_reg="λόγος" postag_reg="n-s---ma-" relation_reg="ADV" head_reg="10" tp_n="1" line_n="2" lang="grc" hand_id="16" tm_word_id=""/>
    <word id="12" form_orig="," form_reg="," lemma_orig="punc1" postag_orig="u--------" relation_orig="AuxX" head_orig="13" lemma_reg="punc1" postag_reg="u--------" relation_reg="AuxX" head_reg="13" tp_n="1" line_n="2" lang="grc" hand_id="17" tm_word_id=""/>
    <word id="13" form_orig="εἴη" form_reg="εἴη" lemma_orig="εἰμί" postag_orig="v3spoa---" relation_orig="PRED" head_orig="0" lemma_reg="εἰμί" postag_reg="v3spoa---" relation_reg="PRED" head_reg="0" tp_n="1" line_n="2" lang="grc" hand_id="18" tm_word_id=""/>
    <word id="14" form_orig="ἂν" form_reg="ἂν" lemma_orig="ἄν1" postag_orig="d--------" relation_orig="AuxY" head_orig="13" lemma_reg="ἄν1" postag_reg="d--------" relation_reg="AuxY" head_reg="13" tp_n="1" line_n="2" lang="grc" hand_id="19" tm_word_id=""/>
    <word id="15" form_orig="ὡς" form_reg="ὡς" lemma_orig="ὡς" postag_orig="c--------" relation_orig="AuxC" head_orig="13" lemma_reg="ὡς" postag_reg="c--------" relation_reg="AuxC" head_reg="13" tp_n="1" line_n="2" lang="grc" hand_id="20" tm_word_id=""/>
    <word id="16" form_orig="ἡμεῖς" form_reg="ἡμεῖς" lemma_orig="ἐγώ" postag_orig="p1p---mn-" relation_orig="SBJ" head_orig="17" lemma_reg="ἐγώ" postag_reg="p1p---mn-" relation_reg="SBJ" head_reg="17" tp_n="1" line_n="2" lang="grc" hand_id="21" tm_word_id=""/>
    <word id="17" form_orig="θέλομ[εν]" form_reg="θέλομεν" lemma_orig="ἐθέλω" postag_orig="v1_p__---" relation_orig="ADV" head_orig="15" lemma_reg="ἐθέλω" postag_reg="v1ppia---" relation_reg="ADV" head_reg="15" tp_n="1" line_n="2" lang="grc" hand_id="22" tm_word_id=""/>
    <word id="18" form_orig="[·]" form_reg="·" lemma_orig="" postag_orig="" relation_orig="" head_orig="" lemma_reg="punc1" postag_reg="u--------" relation_reg="AuxK" head_reg="0" tp_n="1" line_n="2" lang="grc" hand_id="23" tm_word_id=""/>
  </sentence>
  <sentence id="3">
    <word id="1" form_orig="[ὑγιαίνομεν]" form_reg="ὑγιαίνομεν" lemma_orig="" postag_orig="" relation_orig="" head_orig="" lemma_reg="ὑγιαίνω" postag_reg="v1ppia---" relation_reg="PRED_CO" head_reg="6" tp_n="1" line_n="2" lang="grc" hand_id="24" tm_word_id=""/>
    <word id="2" form_orig="[δὲ]" form_reg="δὲ" lemma_orig="" postag_orig="" relation_orig="" head_orig="" lemma_reg="δέ" postag_reg="c--------" relation_reg="COORD" head_reg="0" tp_n="1" line_n="2" lang="grc" hand_id="25" tm_word_id=""/>
    <word id="3" form_orig="καὶ" form_reg="καὶ" lemma_orig="καί" postag_orig="d-------_" relation_orig="AuxZ" head_orig="4" lemma_reg="καί" postag_reg="d-------_" relation_reg="AuxZ" head_reg="4" tp_n="1" line_n="2" lang="grc" hand_id="26" tm_word_id=""/>
    <word id="4" form_orig="αὐτοί" form_reg="αὐτοί" lemma_orig="αὐτός" postag_orig="p-p---mn-" relation_orig="" head_orig="" lemma_reg="αὐτός" postag_reg="p-p---mn-" relation_reg="SBJ" head_reg="1" tp_n="1" line_n="2" lang="grc" hand_id="27" tm_word_id=""/>
    <word id="5" form_orig="," form_reg="," lemma_orig="punc1" postag_orig="u--------" relation_orig="AuxX" head_orig="0" lemma_reg="punc1" postag_reg="u--------" relation_reg="AuxX" head_reg="6" tp_n="1" line_n="2" lang="grc" hand_id="28" tm_word_id=""/>
    <word id="6" form_orig="καὶ" form_reg="καὶ" lemma_orig="καί" postag_orig="c--------" relation_orig="COORD" head_orig="" lemma_reg="καί" postag_reg="c--------" relation_reg="COORD" head_reg="2" tp_n="1" line_n="2" lang="grc" hand_id="29" tm_word_id=""/>
    <word id="7" form_orig="σοῦ" form_reg="σοῦ" lemma_orig="σύ" postag_orig="p2s---mg-" relation_orig="ATR" head_orig="12" lemma_reg="σύ" postag_reg="p2s---mg-" relation_reg="ATR" head_reg="12" tp_n="1" line_n="2" lang="grc" hand_id="30" tm_word_id=""/>
    <word id="8" form_orig="διατελοῦμεν" form_reg="διατελοῦμεν" lemma_orig="διατελέω" postag_orig="v1ppia---" relation_orig="PRED_CO" head_orig="6" lemma_reg="διατελέω" postag_reg="v1ppia---" relation_reg="PRED_CO" head_reg="6" tp_n="1" line_n="2" lang="grc" hand_id="31" tm_word_id=""/>
    <word id="9" form_orig="∼εμ∽" form_reg="ἐν" lemma_orig="ἐν" postag_orig="r--------" relation_orig="AuxP" head_orig="8" lemma_reg="ἐν" postag_reg="r--------" relation_reg="AuxP" head_reg="8" tp_n="1" line_n="3" lang="grc" hand_id="32" tm_word_id=""/>
    <word id="10" form_orig="παντὶ" form_reg="παντὶ" lemma_orig="πᾶς" postag_orig="a-s---md-" relation_orig="ATR" head_orig="11" lemma_reg="πᾶς" postag_reg="a-s---md-" relation_reg="ATR" head_reg="11" tp_n="1" line_n="3" lang="grc" hand_id="33" tm_word_id=""/>
    <word id="11" form_orig="καιρῶι" form_reg="καιρῶι" lemma_orig="καιρός" postag_orig="n-s---md-" relation_orig="ADV" head_orig="9" lemma_reg="καιρός" postag_reg="n-s---md-" relation_reg="ADV" head_reg="9" tp_n="1" line_n="3" lang="grc" hand_id="34" tm_word_id=""/>
    <word id="12" form_orig="μνείαν" form_reg="μνείαν" lemma_orig="μνεία" postag_orig="n-s---fa-" relation_orig="OBJ" head_orig="13" lemma_reg="μνεία" postag_reg="n-s---fa-" relation_reg="OBJ" head_reg="13" tp_n="1" line_n="3" lang="grc" hand_id="35" tm_word_id=""/>
    <word id="13" form_orig="ποιούμ[ενοι]" form_reg="ποιούμενοι" lemma_orig="ποιέω" postag_orig="v__p__---" relation_orig="PNOM" head_orig="8" lemma_reg="ποιέω" postag_reg="v-pppemn-" relation_reg="PNOM" head_reg="8" tp_n="1" line_n="3" lang="grc" hand_id="36" tm_word_id=""/>
    <word id="14" form_orig="[.]" form_reg="." lemma_orig="punc1" postag_orig="u--------" relation_orig="AuxK" head_orig="0" lemma_reg="punc1" postag_reg="u--------" relation_reg="AuxK" head_reg="0" tp_n="1" line_n="3" lang="grc" hand_id="37" tm_word_id=""/>
  </sentence>
  <sentence id="4">
    <word id="1" form_orig="[περὶ]" form_reg="περὶ" lemma_orig="" postag_orig="" relation_orig="" head_orig="" lemma_reg="περί" postag_reg="r--------" relation_reg="AuxP" head_reg="4" tp_n="1" line_n="3" lang="grc" hand_id="38" tm_word_id=""/>
    <word id="2" form_orig="[τοῦ]" form_reg="τοῦ" lemma_orig="" postag_orig="" relation_orig="" head_orig="" lemma_reg="ὁ" postag_reg="l-s---ng-" relation_reg="ATR" head_reg="3" tp_n="1" line_n="3" lang="grc" hand_id="39" tm_word_id=""/>
    <word id="3" form_orig="[ἱππ]α̣ρ̣ίου" form_reg="ἱππαρίου" lemma_orig="" postag_orig="" relation_orig="" head_orig="" lemma_reg="ἱππάριον" postag_reg="n-s---ng-" relation_reg="OBJ" head_reg="1" tp_n="1" line_n="3" lang="grc" hand_id="40" tm_word_id=""/>
    <word id="4" form_orig="ἠξιοῦμεν" form_reg="ἠξιοῦμεν" lemma_orig="ἀξιόω" postag_orig="v1piia---" relation_orig="PRED" head_orig="0" lemma_reg="ἀξιόω" postag_reg="v1piia---" relation_reg="PRED" head_reg="0" tp_n="1" line_n="3" lang="grc" hand_id="41" tm_word_id=""/>
    <word id="5" form_orig="Νικάνορα" form_reg="Νικάνορα" lemma_orig="Νικάνωρ" postag_orig="n-s---ma-" relation_orig="OBJ" head_orig="4" lemma_reg="Νικάνωρ" postag_reg="n-s---ma-" relation_reg="OBJ" head_reg="4" tp_n="1" line_n="3" lang="grc" hand_id="42" tm_word_id=""/>
    <word id="6" form_orig="ὅπως" form_reg="ὅπως" lemma_orig="ὅπως" postag_orig="c--------" relation_orig="AuxC" head_orig="4" lemma_reg="ὅπως" postag_reg="c--------" relation_reg="AuxC" head_reg="4" tp_n="1" line_n="3" lang="grc" hand_id="43" tm_word_id=""/>
    <word id="7" form_orig="ἀλλάξηι" form_reg="ἀλλάξηι" lemma_orig="ἀλλάσσω" postag_orig="v3sasa---" relation_orig="ADV" head_orig="6" lemma_reg="ἀλλάσσω" postag_reg="v3sasa---" relation_reg="ADV" head_reg="6" tp_n="1" line_n="4" lang="grc" hand_id="44" tm_word_id=""/>
    <word id="8" form_orig="ἡμῖν" form_reg="ἡμῖν" lemma_orig="ἐγώ" postag_orig="p1p---md-" relation_orig="OBJ" head_orig="7" lemma_reg="ἐγώ" postag_reg="p1p---md-" relation_reg="OBJ" head_reg="7" tp_n="1" line_n="4" lang="grc" hand_id="45" tm_word_id=""/>
    <word id="9" form_orig="." form_reg="." lemma_orig="punc1" postag_orig="u--------" relation_orig="AuxK" head_orig="0" lemma_reg="punc1" postag_reg="u--------" relation_reg="AuxK" head_reg="0" tp_n="1" line_n="4" lang="grc" hand_id="46" tm_word_id=""/>
  </sentence>
  <sentence id="5">
    <word id="1" form_orig="ἐπεὶ" form_reg="ἐπεὶ" lemma_orig="ἐπεί" postag_orig="c--------" relation_orig="" head_orig="" lemma_reg="ἐπεί" postag_reg="c--------" relation_reg="AuxC" head_reg="6" tp_n="1" line_n="4" lang="grc" hand_id="47" tm_word_id=""/>
    <word id="2" form_orig="οὖν" form_reg="οὖν" lemma_orig="οὖν" postag_orig="d--------" relation_orig="AuxY" head_orig="4" lemma_reg="οὖν" postag_reg="d--------" relation_reg="AuxY" head_reg="4" tp_n="1" line_n="4" lang="grc" hand_id="48" tm_word_id=""/>
    <word id="3" form_orig="οὐκ" form_reg="οὐκ" lemma_orig="οὐ" postag_orig="d--------" relation_orig="AuxZ" head_orig="4" lemma_reg="οὐ" postag_reg="d--------" relation_reg="AuxZ" head_reg="4" tp_n="1" line_n="4" lang="grc" hand_id="49" tm_word_id=""/>
    <word id="4" form_orig="ἐπεχώρει" form_reg="ἐπεχώρει" lemma_orig="ἐπιχωρέω" postag_orig="v3siia---" relation_orig="ADV" head_orig="1" lemma_reg="ἐπιχωρέω" postag_reg="v3siia---" relation_reg="ADV" head_reg="1" tp_n="1" line_n="4" lang="grc" hand_id="50" tm_word_id=""/>
    <word id="5" form_orig="," form_reg="," lemma_orig="punc1" postag_orig="u--------" relation_orig="AuxX" head_orig="0" lemma_reg="punc1" postag_reg="u--------" relation_reg="AuxX" head_reg="6" tp_n="1" line_n="4" lang="grc" hand_id="51" tm_word_id=""/>
    <word id="6" form_orig="[ἠναγκάσθημ]ε̣ν̣" form_reg="ἠναγκάσθημεν" lemma_orig="" postag_orig="" relation_orig="" head_orig="" lemma_reg="ἀναγκάζω" postag_reg="v1paip---" relation_reg="PRED" head_reg="0" tp_n="1" line_n="4" lang="grc" hand_id="52" tm_word_id=""/>
    <word id="7" form_orig="ἀγοράσαντες" form_reg="ἀγοράσαντες" lemma_orig="ἀγοράζω" postag_orig="v-papamn-" relation_orig="" head_orig="" lemma_reg="ἀγοράζω" postag_reg="v-papamn-" relation_reg="ADV" head_reg="6" tp_n="1" line_n="4" lang="grc" hand_id="53" tm_word_id=""/>
    <word id="8" form_orig="❨(δραχμῶν)❩" form_reg="δραχμῶν" lemma_orig="δραχμή" postag_orig="n-_---f_-" relation_orig="ADV" head_orig="7" lemma_reg="δραχμή" postag_reg="n-p---fg-" relation_reg="ADV" head_reg="7" tp_n="1" line_n="4" lang="grc" hand_id="54" tm_word_id=""/>
    <word id="9" form_orig="ω|num:800|" form_reg="ω|num:800|" lemma_orig="ω" postag_orig="m-_---__-" relation_orig="ATR" head_orig="8" lemma_reg="ω" postag_reg="m-_---__-" relation_reg="ATR" head_reg="8" tp_n="1" line_n="4" lang="grc" hand_id="55" tm_word_id=""/>
    <word id="10" form_orig="ἵππον" form_reg="ἵππον" lemma_orig="ἵππος" postag_orig="n-s---ma-" relation_orig="OBJ" head_orig="11" lemma_reg="ἵππος" postag_reg="n-s---ma-" relation_reg="OBJ" head_reg="11" tp_n="1" line_n="4" lang="grc" hand_id="56" tm_word_id=""/>
    <word id="11" form_orig="ἐπικαῦσαι" form_reg="ἐπικαῦσαι" lemma_orig="ἐπικαίω" postag_orig="v--ana---" relation_orig="" head_orig="" lemma_reg="ἐπικαίω" postag_reg="v--ana---" relation_reg="OBJ" head_reg="6" tp_n="1" line_n="4" lang="grc" hand_id="57" tm_word_id=""/>
    <word id="12" form_orig="." form_reg="." lemma_orig="punc1" postag_orig="u--------" relation_orig="AuxK" head_orig="0" lemma_reg="punc1" postag_reg="u--------" relation_reg="AuxK" head_reg="0" tp_n="1" line_n="4" lang="grc" hand_id="58" tm_word_id=""/>
  </sentence>
  <sentence id="6">
    <word id="1" form_orig="ὁ" form_reg="ὁ" lemma_orig="ὁ" postag_orig="l-s---mn-" relation_orig="ATR" head_orig="5" lemma_reg="ὁ" postag_reg="l-s---mn-" relation_reg="ATR" head_reg="5" tp_n="1" line_n="5" lang="grc" hand_id="59" tm_word_id=""/>
    <word id="2" form_orig="δὲ" form_reg="δὲ" lemma_orig="δέ" postag_orig="c--------" relation_orig="COORD" head_orig="0" lemma_reg="δέ" postag_reg="c--------" relation_reg="COORD" head_reg="0" tp_n="1" line_n="5" lang="grc" hand_id="60" tm_word_id=""/>
    <word id="3" form_orig="παρὰ" form_reg="παρὰ" lemma_orig="παρά" postag_orig="r--------" relation_orig="AuxP" head_orig="5" lemma_reg="παρά" postag_reg="r--------" relation_reg="AuxP" head_reg="5" tp_n="1" line_n="5" lang="grc" hand_id="61" tm_word_id=""/>
    <word id="4" form_orig="σοῦ" form_reg="σοῦ" lemma_orig="σύ" postag_orig="p2s---mg-" relation_orig="ATR" head_orig="3" lemma_reg="σύ" postag_reg="p2s---mg-" relation_reg="ATR" head_reg="3" tp_n="1" line_n="5" lang="grc" hand_id="62" tm_word_id=""/>
    <word id="5" form_orig="ἵππος" form_reg="ἵππος" lemma_orig="ἵππος" postag_orig="n-s---mn-" relation_orig="SBJ" head_orig="6" lemma_reg="ἵππος" postag_reg="n-s---mn-" relation_reg="SBJ" head_reg="6" tp_n="1" line_n="5" lang="grc" hand_id="63" tm_word_id=""/>
    <word id="6" form_orig="κατέφθαρται" form_reg="κατέφθαρται" lemma_orig="καταφθείρω" postag_orig="v3srie---" relation_orig="PRED_CO" head_orig="25" lemma_reg="καταφθείρω" postag_reg="v3srie---" relation_reg="PRED_CO" head_reg="25" tp_n="1" line_n="5" lang="grc" hand_id="64" tm_word_id=""/>
    <word id="7" form_orig="καὶ" form_reg="καὶ" lemma_orig="καί" postag_orig="c--------" relation_orig="AuxY" head_orig="25" lemma_reg="καί" postag_reg="c--------" relation_reg="AuxY" head_reg="25" tp_n="1" line_n="5" lang="grc" hand_id="65" tm_word_id=""/>
    <word id="8" form_orig="τ̣η̣|gap:5|" form_reg="τη|gap:5|" lemma_orig="" postag_orig="" relation_orig="" head_orig="" lemma_reg="" postag_reg="" relation_reg="" head_reg="" tp_n="1" line_n="5" lang="grc" hand_id="66" tm_word_id=""/>
    <word id="9" form_orig="[παρ]ε̣γ̣έ̣ν̣ετο" form_reg="παρεγένετο" lemma_orig="-γίγνομαι?" postag_orig="v3saim---" relation_orig="PRED_CO" head_orig="25" lemma_reg="παραγίγνομαι" postag_reg="v3saim---" relation_reg="PRED_CO" head_reg="25" tp_n="1" line_n="5" lang="grc" hand_id="67" tm_word_id=""/>
    <word id="10" form_orig="δὲ" form_reg="δὲ" lemma_orig="δέ" postag_orig="d--------" relation_orig="AuxY" head_orig="9" lemma_reg="δέ" postag_reg="d--------" relation_reg="AuxY" head_reg="9" tp_n="1" line_n="5" lang="grc" hand_id="68" tm_word_id=""/>
    <word id="11" form_orig="καὶ" form_reg="καὶ" lemma_orig="καί" postag_orig="d-------_" relation_orig="AuxZ" head_orig="12" lemma_reg="καί" postag_reg="d-------_" relation_reg="AuxZ" head_reg="12" tp_n="1" line_n="5" lang="grc" hand_id="69" tm_word_id=""/>
    <word id="12" form_orig="Ἀπολλοφάνης" form_reg="Ἀπολλοφάνης" lemma_orig="Ἀπολλοφάνης" postag_orig="n-s---mn-" relation_orig="SBJ" head_orig="9" lemma_reg="Ἀπολλοφάνης" postag_reg="n-s---mn-" relation_reg="SBJ" head_reg="9" tp_n="1" line_n="5" lang="grc" hand_id="70" tm_word_id=""/>
    <word id="13" form_orig="εἰς" form_reg="εἰς" lemma_orig="εἰς" postag_orig="r--------" relation_orig="AuxP" head_orig="9" lemma_reg="εἰς" postag_reg="r--------" relation_reg="AuxP" head_reg="9" tp_n="1" line_n="5" lang="grc" hand_id="71" tm_word_id=""/>
    <word id="14" form_orig="Συρίαν" form_reg="Συρίαν" lemma_orig="Συρία" postag_orig="n-s---fa-" relation_orig="OBJ" head_orig="13" lemma_reg="Συρία" postag_reg="n-s---fa-" relation_reg="OBJ" head_reg="13" tp_n="1" line_n="5" lang="grc" hand_id="72" tm_word_id=""/>
    <word id="15" form_orig="," form_reg="," lemma_orig="punc1" postag_orig="u--------" relation_orig="AuxX" head_orig="25" lemma_reg="punc1" postag_reg="u--------" relation_reg="AuxX" head_reg="25" tp_n="1" line_n="5" lang="grc" hand_id="73" tm_word_id=""/>
    <word id="16" form_orig="καὶ" form_reg="καὶ" lemma_orig="καί" postag_orig="c--------" relation_orig="AuxY" head_orig="25" lemma_reg="καί" postag_reg="c--------" relation_reg="AuxY" head_reg="25" tp_n="1" line_n="6" lang="grc" hand_id="74" tm_word_id=""/>
    <word id="17" form_orig="ἀποδημοῦντες" form_reg="ἀποδημοῦντες" lemma_orig="ἀποδημέω" postag_orig="v-pppamn-" relation_orig="" head_orig="" lemma_reg="ἀποδημέω" postag_reg="v-pppamn-" relation_reg="ADV" head_reg="21" tp_n="1" line_n="6" lang="grc" hand_id="75" tm_word_id=""/>
    <word id="18" form_orig="ἡμεῖς" form_reg="ἡμεῖς" lemma_orig="ἐγώ" postag_orig="p1p---mn-" relation_orig="SBJ" head_orig="17" lemma_reg="ἐγώ" postag_reg="p1p---mn-" relation_reg="SBJ" head_reg="17" tp_n="1" line_n="6" lang="grc" hand_id="76" tm_word_id=""/>
    <word id="19" form_orig="εἰς" form_reg="εἰς" lemma_orig="εἰς" postag_orig="r--------" relation_orig="AuxP" head_orig="17" lemma_reg="εἰς" postag_reg="r--------" relation_reg="AuxP" head_reg="17" tp_n="1" line_n="6" lang="grc" hand_id="77" tm_word_id=""/>
    <word id="20" form_orig="Μασσύαν" form_reg="Μασσύαν" lemma_orig="Μασσύας" postag_orig="n-s---fa-" relation_orig="ADV" head_orig="19" lemma_reg="Μασσύας" postag_reg="n-s---fa-" relation_reg="ADV" head_reg="19" tp_n="1" line_n="6" lang="grc" hand_id="78" tm_word_id=""/>
    <word id="21" form_orig="[συνηντῶμεν]" form_reg="συνηντῶμεν" lemma_orig="" postag_orig="" relation_orig="" head_orig="" lemma_reg="συναντάω" postag_reg="v1piia---" relation_reg="PRED_CO" head_reg="25" tp_n="1" line_n="6" lang="grc" hand_id="79" tm_word_id=""/>
    <word id="22" form_orig="αὐτῶι" form_reg="αὐτῶι" lemma_orig="αὐτός" postag_orig="p-s---md-" relation_orig="" head_orig="" lemma_reg="αὐτός" postag_reg="p-s---md-" relation_reg="OBJ" head_reg="21" tp_n="1" line_n="6" lang="grc" hand_id="80" tm_word_id=""/>
    <word id="23" form_orig="ἐν" form_reg="ἐν" lemma_orig="ἐν" postag_orig="r--------" relation_orig="AuxP" head_orig="" lemma_reg="ἐν" postag_reg="r--------" relation_reg="AuxP" head_reg="21" tp_n="1" line_n="6" lang="grc" hand_id="81" tm_word_id=""/>
    <word id="24" form_orig="Σιδῶνι" form_reg="Σιδῶνι" lemma_orig="Σιδών" postag_orig="n-s---fd-" relation_orig="" head_orig="23" lemma_reg="Σιδών" postag_reg="n-s---fd-" relation_reg="ADV" head_reg="23" tp_n="1" line_n="6" lang="grc" hand_id="82" tm_word_id=""/>
    <word id="25" form_orig="καὶ" form_reg="καὶ" lemma_orig="καί" postag_orig="c--------" relation_orig="COORD" head_orig="2" lemma_reg="καί" postag_reg="c--------" relation_reg="COORD" head_reg="2" tp_n="1" line_n="6" lang="grc" hand_id="83" tm_word_id=""/>
    <word id="26" form_orig="ἀνήγγε̣λ̣λ̣ε̣ν̣" form_reg="ἀνήγγελλεν" lemma_orig="ἀναγγέλλω" postag_orig="v3saia---" relation_orig="PRED_CO" head_orig="25" lemma_reg="ἀναγγέλλω" postag_reg="v3saia---" relation_reg="PRED_CO" head_reg="25" tp_n="1" line_n="6" lang="grc" hand_id="84" tm_word_id=""/>
    <word id="27" form_orig="ἡ̣μ̣ῖ̣ν̣" form_reg="ἡμῖν" lemma_orig="ἐγώ" postag_orig="p1p---md-" relation_orig="OBJ" head_orig="26" lemma_reg="ἐγώ" postag_reg="p1p---md-" relation_reg="OBJ" head_reg="26" tp_n="1" line_n="6" lang="grc" hand_id="85" tm_word_id=""/>
    <word id="28" form_orig="ὅτι" form_reg="ὅτι" lemma_orig="ὅτι2" postag_orig="c--------" relation_orig="AuxC" head_orig="26" lemma_reg="ὅτι2" postag_reg="c--------" relation_reg="AuxC" head_reg="26" tp_n="1" line_n="7" lang="grc" hand_id="86" tm_word_id=""/>
    <word id="29" form_orig="Κρότος" form_reg="Κρότος" lemma_orig="Κρότος" postag_orig="n-s---mn-" relation_orig="SBJ" head_orig="32" lemma_reg="Κρότος" postag_reg="n-s---mn-" relation_reg="SBJ" head_reg="32" tp_n="1" line_n="7" lang="grc" hand_id="87" tm_word_id=""/>
    <word id="30" form_orig="ἐν" form_reg="ἐν" lemma_orig="ἐν" postag_orig="r--------" relation_orig="AuxP" head_orig="32" lemma_reg="ἐν" postag_reg="r--------" relation_reg="AuxP" head_reg="32" tp_n="1" line_n="7" lang="grc" hand_id="88" tm_word_id=""/>
    <word id="31" form_orig="Ἰόπηι" form_reg="Ἰόπηι" lemma_orig="Ἰόπη" postag_orig="n-s---fd-" relation_orig="ADV" head_orig="30" lemma_reg="Ἰόπη" postag_reg="n-s---fd-" relation_reg="ADV" head_reg="30" tp_n="1" line_n="7" lang="grc" hand_id="89" tm_word_id=""/>
    <word id="32" form_orig="ἐστὶν" form_reg="ἐστὶν" lemma_orig="εἰμί" postag_orig="v3spia---" relation_orig="OBJ" head_orig="28" lemma_reg="εἰμί" postag_reg="v3spia---" relation_reg="OBJ" head_reg="28" tp_n="1" line_n="7" lang="grc" hand_id="90" tm_word_id=""/>
    <word id="33" form_orig="βουλόμενος" form_reg="βουλόμενος" lemma_orig="βούλομαι" postag_orig="v-sppemn-" relation_orig="ADV" head_orig="32" lemma_reg="βούλομαι" postag_reg="v-sppemn-" relation_reg="ADV" head_reg="32" tp_n="1" line_n="7" lang="grc" hand_id="91" tm_word_id=""/>
    <word id="34" form_orig="σώματα" form_reg="σώματα" lemma_orig="σῶμα" postag_orig="n-p---na-" relation_orig="OBJ_CO" head_orig="36" lemma_reg="σῶμα" postag_reg="n-p---na-" relation_reg="OBJ_CO" head_reg="36" tp_n="1" line_n="7" lang="grc" hand_id="92" tm_word_id=""/>
    <word id="35" form_orig="ἐξαποστεῖλαι" form_reg="ἐξαποστεῖλαι" lemma_orig="ἐξαποστέλλω" postag_orig="v--ana---" relation_orig="OBJ" head_orig="33" lemma_reg="ἐξαποστέλλω" postag_reg="v--ana---" relation_reg="OBJ" head_reg="33" tp_n="1" line_n="7" lang="grc" hand_id="93" tm_word_id=""/>
    <word id="36" form_orig="καὶ" form_reg="καὶ" lemma_orig="καί" postag_orig="c--------" relation_orig="COORD" head_orig="35" lemma_reg="καί" postag_reg="c--------" relation_reg="COORD" head_reg="35" tp_n="1" line_n="7" lang="grc" hand_id="94" tm_word_id=""/>
    <word id="37" form_orig="στρώματα" form_reg="στρώματα" lemma_orig="στρῶμα" postag_orig="n-p---na-" relation_orig="OBJ_CO" head_orig="36" lemma_reg="στρῶμα" postag_reg="n-p---na-" relation_reg="OBJ_CO" head_reg="36" tp_n="1" line_n="7" lang="grc" hand_id="95" tm_word_id=""/>
    <word id="38" form_orig="." form_reg="." lemma_orig="punc1" postag_orig="u--------" relation_orig="AuxK" head_orig="0" lemma_reg="punc1" postag_reg="u--------" relation_reg="AuxK" head_reg="0" tp_n="1" line_n="7" lang="grc" hand_id="96" tm_word_id=""/>
  </sentence>
  <sentence id="7">
    <word id="1" form_orig="οὐκ" form_reg="οὐκ" lemma_orig="οὐ" postag_orig="d--------" relation_orig="AuxZ" head_orig="4" lemma_reg="οὐ" postag_reg="d--------" relation_reg="AuxZ" head_reg="4" tp_n="1" line_n="8" lang="grc" hand_id="97" tm_word_id=""/>
    <word id="2" form_orig="ἔφη" form_reg="ἔφη" lemma_orig="φημί" postag_orig="v3siia---" relation_orig="PRED" head_orig="0" lemma_reg="φημί" postag_reg="v3siia---" relation_reg="PRED" head_reg="0" tp_n="1" line_n="8" lang="grc" hand_id="98" tm_word_id=""/>
    <word id="3" form_orig="οὖν" form_reg="οὖν" lemma_orig="οὖν" postag_orig="d--------" relation_orig="AuxY" head_orig="2" lemma_reg="οὖν" postag_reg="d--------" relation_reg="AuxY" head_reg="2" tp_n="1" line_n="8" lang="grc" hand_id="99" tm_word_id=""/>
    <word id="4" form_orig="δύνασθαι" form_reg="δύνασθαι" lemma_orig="δύναμαι" postag_orig="v--pne---" relation_orig="OBJ" head_orig="2" lemma_reg="δύναμαι" postag_reg="v--pne---" relation_reg="OBJ" head_reg="2" tp_n="1" line_n="8" lang="grc" hand_id="100" tm_word_id=""/>
    <word id="5" form_orig="οὐκέτι" form_reg="οὐκέτι" lemma_orig="οὐκέτι" postag_orig="d--------" relation_orig="AuxZ" head_orig="6" lemma_reg="οὐκέτι" postag_reg="d--------" relation_reg="AuxZ" head_reg="6" tp_n="1" line_n="8" lang="grc" hand_id="101" tm_word_id=""/>
    <word id="6" form_orig="παραπλ[εῖν]" form_reg="παραπλεῖν" lemma_orig="παραπλέω" postag_orig="v____a---" relation_orig="OBJ" head_orig="4" lemma_reg="παραπλέω" postag_reg="v--pna---" relation_reg="OBJ" head_reg="4" tp_n="1" line_n="8" lang="grc" hand_id="102" tm_word_id=""/>
    <word id="7" form_orig="[·]" form_reg="·" lemma_orig="" postag_orig="" relation_orig="" head_orig="" lemma_reg="punc1" postag_reg="u--------" relation_reg="AuxK" head_reg="0" tp_n="1" line_n="8" lang="grc" hand_id="103" tm_word_id=""/>
  </sentence>
  <sentence id="8">
    <word id="1" form_orig="[συντετάχ]θ̣α̣ι̣" form_reg="συντετάχθαι" lemma_orig="" postag_orig="" relation_orig="" head_orig="" lemma_reg="συντάσσω" postag_reg="v--rne---" relation_reg="PNOM" head_reg="12" tp_n="1" line_n="8" lang="grc" hand_id="104" tm_word_id=""/>
    <word id="2" form_orig="γὰρ" form_reg="γὰρ" lemma_orig="γάρ" postag_orig="d--------" relation_orig="" head_orig="" lemma_reg="γάρ" postag_reg="d--------" relation_reg="AuxY" head_reg="12" tp_n="1" line_n="8" lang="grc" hand_id="105" tm_word_id=""/>
    <word id="3" form_orig="ὑπὸ" form_reg="ὑπὸ" lemma_orig="ὑπό" postag_orig="r--------" relation_orig="" head_orig="" lemma_reg="ὑπό" postag_reg="r--------" relation_reg="AuxP" head_reg="1" tp_n="1" line_n="8" lang="grc" hand_id="106" tm_word_id=""/>
    <word id="4" form_orig="Διονυσοδώρου" form_reg="Διονυσοδώρου" lemma_orig="Διονυσόδωρος" postag_orig="n-s---mg-" relation_orig="" head_orig="3" lemma_reg="Διονυσόδωρος" postag_reg="n-s---mg-" relation_reg="OBJ" head_reg="3" tp_n="1" line_n="8" lang="grc" hand_id="107" tm_word_id=""/>
    <word id="5" form_orig="τὴν" form_reg="τὴν" lemma_orig="ὁ" postag_orig="l-s---fa-" relation_orig="ATR" head_orig="6" lemma_reg="ὁ" postag_reg="l-s---fa-" relation_reg="ATR" head_reg="6" tp_n="1" line_n="9" lang="grc" hand_id="108" tm_word_id=""/>
    <word id="6" form_orig="ἀποσκευὴν" form_reg="ἀποσκευὴν" lemma_orig="ἀποσκευή" postag_orig="n-s---fa-" relation_orig="OBJ" head_orig="8" lemma_reg="ἀποσκευή" postag_reg="n-s---fa-" relation_reg="OBJ" head_reg="8" tp_n="1" line_n="9" lang="grc" hand_id="109" tm_word_id=""/>
    <word id="7" form_orig="αὐτῶι" form_reg="αὐτῶι" lemma_orig="αὐτός" postag_orig="p-s---md-" relation_orig="OBJ" head_orig="8" lemma_reg="αὐτός" postag_reg="p-s---md-" relation_reg="OBJ" head_reg="8" tp_n="1" line_n="9" lang="grc" hand_id="110" tm_word_id=""/>
    <word id="8" form_orig="ἀπαγαγεῖν" form_reg="ἀπαγαγεῖν" lemma_orig="ἀπάγω" postag_orig="v--ana---" relation_orig="" head_orig="" lemma_reg="ἀπάγω" postag_reg="v--ana---" relation_reg="SBJ" head_reg="12" tp_n="1" line_n="9" lang="grc" hand_id="111" tm_word_id=""/>
    <word id="9" form_orig="ε[ἰς]" form_reg="εἰς" lemma_orig="εἰς" postag_orig="r--------" relation_orig="AuxP" head_orig="8" lemma_reg="εἰς" postag_reg="r--------" relation_reg="AuxP" head_reg="8" tp_n="1" line_n="9" lang="grc" hand_id="112" tm_word_id=""/>
    <word id="10" form_orig="[Ἡ]ρ̣ά̣κλειαν" form_reg="Ἡράκλειαν" lemma_orig="Ἡρακλεία" postag_orig="n-s---fa-" relation_orig="ADV" head_orig="9" lemma_reg="Ἡρακλεία" postag_reg="n-s---fa-" relation_reg="ADV" head_reg="9" tp_n="1" line_n="9" lang="grc" hand_id="113" tm_word_id=""/>
    <word id="11" form_orig="." form_reg="." lemma_orig="punc1" postag_orig="u--------" relation_orig="AuxK" head_orig="0" lemma_reg="punc1" postag_reg="u--------" relation_reg="AuxK" head_reg="0" tp_n="1" line_n="9" lang="grc" hand_id="114" tm_word_id=""/>
    <word id="12" form_orig="[0]" form_reg="[0]" lemma_orig="" postag_orig="" relation_orig="" head_orig="" lemma_reg="" postag_reg="" relation_reg="PRED" head_reg="0" insertion_id="0000e" artificial="elliptic" tp_n="" line_n="None" lang="None" hand_id="115" tm_word_id=""/>
  </sentence>
  <sentence id="9">
    <word id="1" form_orig="ἀνήγγελλεν" form_reg="ἀνήγγελλεν" lemma_orig="ἀναγγέλλω" postag_orig="v3saia---" relation_orig="PRED_CO" head_orig="2" lemma_reg="ἀναγγέλλω" postag_reg="v3saia---" relation_reg="PRED_CO" head_reg="2" tp_n="1" line_n="9" lang="grc" hand_id="116" tm_word_id=""/>
    <word id="2" form_orig="δὲ" form_reg="δὲ" lemma_orig="δέ" postag_orig="c--------" relation_orig="COORD" head_orig="0" lemma_reg="δέ" postag_reg="c--------" relation_reg="COORD" head_reg="0" tp_n="1" line_n="9" lang="grc" hand_id="117" tm_word_id=""/>
    <word id="3" form_orig="ἡμῖν" form_reg="ἡμῖν" lemma_orig="ἐγώ" postag_orig="p1p---md-" relation_orig="OBJ" head_orig="1" lemma_reg="ἐγώ" postag_reg="p1p---md-" relation_reg="OBJ" head_reg="1" tp_n="1" line_n="9" lang="grc" hand_id="118" tm_word_id=""/>
    <word id="4" form_orig="καὶ" form_reg="καὶ" lemma_orig="καί" postag_orig="d-------_" relation_orig="AuxZ" head_orig="6" lemma_reg="καί" postag_reg="d-------_" relation_reg="AuxZ" head_reg="6" tp_n="1" line_n="10" lang="grc" hand_id="119" tm_word_id=""/>
    <word id="5" form_orig="περὶ" form_reg="περὶ" lemma_orig="περί" postag_orig="r--------" relation_orig="AuxP" head_orig="1" lemma_reg="περί" postag_reg="r--------" relation_reg="AuxP" head_reg="1" tp_n="1" line_n="10" lang="grc" hand_id="120" tm_word_id=""/>
    <word id="6" form_orig="τῶν" form_reg="τῶν" lemma_orig="ὁ" postag_orig="p-p---mg-" relation_orig="OBJ" head_orig="5" lemma_reg="ὁ" postag_reg="p-p---mg-" relation_reg="OBJ" head_reg="5" tp_n="1" line_n="10" lang="grc" hand_id="121" tm_word_id=""/>
    <word id="7" form_orig="ἐν" form_reg="ἐν" lemma_orig="ἐν" postag_orig="r--------" relation_orig="AuxP" head_orig="6" lemma_reg="ἐν" postag_reg="r--------" relation_reg="AuxP" head_reg="6" tp_n="1" line_n="10" lang="grc" hand_id="122" tm_word_id=""/>
    <word id="8" form_orig="οἴκωι" form_reg="οἴκωι" lemma_orig="οἶκος" postag_orig="n-s---md-" relation_orig="ATR" head_orig="7" lemma_reg="οἶκος" postag_reg="n-s---md-" relation_reg="ATR" head_reg="7" tp_n="1" line_n="10" lang="grc" hand_id="123" tm_word_id=""/>
    <word id="9" form_orig="ὅτι" form_reg="ὅτι" lemma_orig="ὅτι2" postag_orig="c--------" relation_orig="AuxC" head_orig="1" lemma_reg="ὅτι2" postag_reg="c--------" relation_reg="AuxC" head_reg="1" tp_n="1" line_n="10" lang="grc" hand_id="124" tm_word_id=""/>
    <word id="10" form_orig="ἔρ̣ρ̣ωντ̣α̣ι̣" form_reg="ἔρρωνται" lemma_orig="ῥώννυμι" postag_orig="v3prie---" relation_orig="OBJ" head_orig="9" lemma_reg="ῥώννυμι" postag_reg="v3prie---" relation_reg="OBJ" head_reg="9" tp_n="1" line_n="10" lang="grc" hand_id="125" tm_word_id=""/>
    <word id="11" form_orig="[πάντ]ε̣ς̣" form_reg="πάντες" lemma_orig="" postag_orig="" relation_orig="" head_orig="" lemma_reg="πᾶς" postag_reg="a-p---mn-" relation_reg="SBJ" head_reg="10" tp_n="1" line_n="10" lang="grc" hand_id="126" tm_word_id=""/>
    <word id="12" form_orig="." form_reg="." lemma_orig="punc1" postag_orig="u--------" relation_orig="AuxK" head_orig="0" lemma_reg="punc1" postag_reg="u--------" relation_reg="AuxK" head_reg="0" tp_n="1" line_n="10" lang="grc" hand_id="127" tm_word_id=""/>
  </sentence>
  <sentence id="10">
    <word id="1" form_orig="κ̣α̣ὶ̣" form_reg="καὶ" lemma_orig="καί" postag_orig="d-------_" relation_orig="AuxZ" head_orig="2" lemma_reg="καί" postag_reg="d-------_" relation_reg="AuxZ" head_reg="2" tp_n="1" line_n="10" lang="grc" hand_id="128" tm_word_id=""/>
    <word id="2" form_orig="Μενεκλῆς" form_reg="Μενεκλῆς" lemma_orig="Μενεκλῆς" postag_orig="n-s---mn-" relation_orig="SBJ" head_orig="7" lemma_reg="Μενεκλῆς" postag_reg="n-s---mn-" relation_reg="SBJ" head_reg="7" tp_n="1" line_n="10" lang="grc" hand_id="129" tm_word_id=""/>
    <word id="3" form_orig="δὲ" form_reg="δὲ" lemma_orig="δέ" postag_orig="c--------" relation_orig="COORD" head_orig="0" lemma_reg="δέ" postag_reg="c--------" relation_reg="COORD" head_reg="0" tp_n="1" line_n="10" lang="grc" hand_id="130" tm_word_id=""/>
    <word id="4" form_orig="ὁ" form_reg="ὁ" lemma_orig="ὁ" postag_orig="p-s---mn-" relation_orig="ATR" head_orig="2" lemma_reg="ὁ" postag_reg="p-s---mn-" relation_reg="ATR" head_reg="2" tp_n="1" line_n="10" lang="grc" hand_id="131" tm_word_id=""/>
    <word id="5" form_orig="ἐν" form_reg="ἐν" lemma_orig="ἐν" postag_orig="r--------" relation_orig="AuxP" head_orig="4" lemma_reg="ἐν" postag_reg="r--------" relation_reg="AuxP" head_reg="4" tp_n="1" line_n="10" lang="grc" hand_id="132" tm_word_id=""/>
    <word id="6" form_orig="Τύρωι" form_reg="Τύρωι" lemma_orig="Τύρος" postag_orig="n-s---fd-" relation_orig="ATR" head_orig="5" lemma_reg="Τύρος" postag_reg="n-s---fd-" relation_reg="ATR" head_reg="5" tp_n="1" line_n="10" lang="grc" hand_id="133" tm_word_id=""/>
    <word id="7" form_orig="ἔφη" form_reg="ἔφη" lemma_orig="φημί" postag_orig="v3siia---" relation_orig="PRED_CO" head_orig="3" lemma_reg="φημί" postag_reg="v3siia---" relation_reg="PRED_CO" head_reg="3" tp_n="1" line_n="11" lang="grc" hand_id="134" tm_word_id=""/>
    <word id="8" form_orig="σωμάτιά" form_reg="σωμάτιά" lemma_orig="σωμάτιον" postag_orig="n-p---na-" relation_orig="OBJ_CO" head_orig="10" lemma_reg="σωμάτιον" postag_reg="n-p---na-" relation_reg="OBJ_CO" head_reg="10" tp_n="1" line_n="11" lang="grc" hand_id="135" tm_word_id=""/>
    <word id="9" form_orig="τινα" form_reg="τινα" lemma_orig="τις" postag_orig="p-p---na-" relation_orig="ATR" head_orig="8" lemma_reg="τις" postag_reg="p-p---na-" relation_reg="ATR" head_reg="8" tp_n="1" line_n="11" lang="grc" hand_id="136" tm_word_id=""/>
    <word id="10" form_orig="καὶ" form_reg="καὶ" lemma_orig="καί" postag_orig="c--------" relation_orig="COORD" head_orig="12" lemma_reg="καί" postag_reg="c--------" relation_reg="COORD" head_reg="12" tp_n="1" line_n="11" lang="grc" hand_id="137" tm_word_id=""/>
    <word id="11" form_orig="φορτία" form_reg="φορτία" lemma_orig="φορτίον" postag_orig="n-p---na-" relation_orig="OBJ_CO" head_orig="10" lemma_reg="φορτίον" postag_reg="n-p---na-" relation_reg="OBJ_CO" head_reg="10" tp_n="1" line_n="11" lang="grc" hand_id="138" tm_word_id=""/>
    <word id="12" form_orig="ἀγαγὼ̣[ν]" form_reg="ἀγαγὼν" lemma_orig="ἄγω" postag_orig="v-sapamn_" relation_orig="ADV" head_orig="18" lemma_reg="ἄγω" postag_reg="v-sapamn-" relation_reg="ADV" head_reg="18" tp_n="1" line_n="11" lang="grc" hand_id="139" tm_word_id=""/>
    <word id="13" form_orig="αὐτὸς" form_reg="αὐτὸς" lemma_orig="αὐτός" postag_orig="p-s---mn-" relation_orig="SBJ" head_orig="12" lemma_reg="αὐτός" postag_reg="p-s---mn-" relation_reg="SBJ" head_reg="12" tp_n="1" line_n="11" lang="grc" hand_id="140" tm_word_id=""/>
    <word id="14" form_orig="ἐκ" form_reg="ἐκ" lemma_orig="ἐκ" postag_orig="r--------" relation_orig="AuxP" head_orig="12" lemma_reg="ἐκ" postag_reg="r--------" relation_reg="AuxP" head_reg="12" tp_n="1" line_n="11" lang="grc" hand_id="141" tm_word_id=""/>
    <word id="15" form_orig="Γάζης" form_reg="Γάζης" lemma_orig="Γάζα" postag_orig="n-s---fg-" relation_orig="ADV" head_orig="14" lemma_reg="Γάζα" postag_reg="n-s---fg-" relation_reg="ADV" head_reg="14" tp_n="1" line_n="11" lang="grc" hand_id="142" tm_word_id=""/>
    <word id="16" form_orig="εἰς" form_reg="εἰς" lemma_orig="εἰς" postag_orig="r--------" relation_orig="AuxP" head_orig="12" lemma_reg="εἰς" postag_reg="r--------" relation_reg="AuxP" head_reg="12" tp_n="1" line_n="11" lang="grc" hand_id="143" tm_word_id=""/>
    <word id="17" form_orig="Τύρον" form_reg="Τύρον" lemma_orig="Τύρος" postag_orig="n-s---fa-" relation_orig="OBJ" head_orig="16" lemma_reg="Τύρος" postag_reg="n-s---fa-" relation_reg="OBJ" head_reg="16" tp_n="1" line_n="11" lang="grc" hand_id="144" tm_word_id=""/>
    <word id="18" form_orig="μετεξελέσθαι" form_reg="μετεξελέσθαι" lemma_orig="μετεξαιρέομαι" postag_orig="v--anm---" relation_orig="OBJ_CO" head_orig="33" lemma_reg="μετεξαιρέομαι" postag_reg="v--anm---" relation_reg="OBJ_CO" head_reg="33" tp_n="1" line_n="12" lang="grc" hand_id="145" tm_word_id=""/>
    <word id="19" form_orig="εἰς" form_reg="εἰς" lemma_orig="εἰς" postag_orig="r--------" relation_orig="AuxP" head_orig="18" lemma_reg="εἰς" postag_reg="r--------" relation_reg="AuxP" head_reg="18" tp_n="1" line_n="12" lang="grc" hand_id="146" tm_word_id=""/>
    <word id="20" form_orig="Τύρον" form_reg="Τύρον" lemma_orig="Τύρος" postag_orig="n-s---fa-" relation_orig="ADV" head_orig="19" lemma_reg="Τύρος" postag_reg="n-s---fa-" relation_reg="ADV" head_reg="19" tp_n="1" line_n="12" lang="grc" hand_id="147" tm_word_id=""/>
    <word id="21" form_orig="," form_reg="," lemma_orig="punc1" postag_orig="u--------" relation_orig="AuxX" head_orig="7" lemma_reg="punc1" postag_reg="u--------" relation_reg="AuxX" head_reg="7" tp_n="1" line_n="12" lang="grc" hand_id="148" tm_word_id=""/>
    <word id="22" form_orig="οὐ" form_reg="οὐ" lemma_orig="οὐ" postag_orig="d--------" relation_orig="AuxZ" head_orig="26" lemma_reg="οὐ" postag_reg="d--------" relation_reg="AuxZ" head_reg="26" tp_n="1" line_n="12" lang="grc" hand_id="149" tm_word_id=""/>
    <word id="23" form_orig="προσαγγεί̣[λαν]τα" form_reg="προσαγγείλαντα" lemma_orig="προσαγγέλλω" postag_orig="v__a__---" relation_orig="ATR_CO" head_orig="26" lemma_reg="προσαγγέλλω" postag_reg="v-sapama-" relation_reg="ATR_CO" head_reg="26" tp_n="1" line_n="12" lang="grc" hand_id="150" tm_word_id=""/>
    <word id="24" form_orig="τοῖς" form_reg="τοῖς" lemma_orig="ὁ" postag_orig="l-p---md-" relation_orig="ATR" head_orig="25" lemma_reg="ὁ" postag_reg="l-p---md-" relation_reg="ATR" head_reg="25" tp_n="1" line_n="12" lang="grc" hand_id="151" tm_word_id=""/>
    <word id="25" form_orig="τελώναις" form_reg="τελώναις" lemma_orig="τελώνης" postag_orig="n-p---md-" relation_orig="OBJ" head_orig="23" lemma_reg="τελώνης" postag_reg="n-p---md-" relation_reg="OBJ" head_reg="23" tp_n="1" line_n="12" lang="grc" hand_id="152" tm_word_id=""/>
    <word id="26" form_orig="οὐδὲ" form_reg="οὐδὲ" lemma_orig="οὐδέ" postag_orig="c--------" relation_orig="COORD" head_orig="36" lemma_reg="οὐδέ" postag_reg="c--------" relation_reg="COORD" head_reg="36" tp_n="1" line_n="12" lang="grc" hand_id="153" tm_word_id=""/>
    <word id="27" form_orig="ἔχοντα" form_reg="ἔχοντα" lemma_orig="ἔχω" postag_orig="v-sppama-" relation_orig="ATR_CO" head_orig="26" lemma_reg="ἔχω" postag_reg="v-sppama-" relation_reg="ATR_CO" head_reg="26" tp_n="1" line_n="12" lang="grc" hand_id="154" tm_word_id=""/>
    <word id="28" form_orig="ἐξαγωγὴν" form_reg="ἐξαγωγὴν" lemma_orig="ἐξαγωγή" postag_orig="n-s---fa-" relation_orig="OBJ" head_orig="27" lemma_reg="ἐξαγωγή" postag_reg="n-s---fa-" relation_reg="OBJ" head_reg="27" tp_n="1" line_n="13" lang="grc" hand_id="155" tm_word_id=""/>
    <word id="29" form_orig="τῶν" form_reg="τῶν" lemma_orig="ὁ" postag_orig="l-p---ng-" relation_orig="ATR" head_orig="30" lemma_reg="ὁ" postag_reg="l-p---ng-" relation_reg="ATR" head_reg="30" tp_n="1" line_n="13" lang="grc" hand_id="156" tm_word_id=""/>
    <word id="30" form_orig="σωμάτων" form_reg="σωμάτων" lemma_orig="σῶμα" postag_orig="n-p---ng-" relation_orig="ATR" head_orig="28" lemma_reg="σῶμα" postag_reg="n-p---ng-" relation_reg="ATR" head_reg="28" tp_n="1" line_n="13" lang="grc" hand_id="157" tm_word_id=""/>
    <word id="31" form_orig="," form_reg="," lemma_orig="punc1" postag_orig="u--------" relation_orig="AuxX" head_orig="33" lemma_reg="punc1" postag_reg="u--------" relation_reg="AuxX" head_reg="33" tp_n="1" line_n="13" lang="grc" hand_id="158" tm_word_id=""/>
    <word id="32" form_orig="τοὺς" form_reg="τοὺς" lemma_orig="ὁ" postag_orig="l-p---ma-" relation_orig="ATR" head_orig="34" lemma_reg="ὁ" postag_reg="l-p---ma-" relation_reg="ATR" head_reg="34" tp_n="1" line_n="13" lang="grc" hand_id="159" tm_word_id=""/>
    <word id="33" form_orig="δὲ" form_reg="δὲ" lemma_orig="δέ" postag_orig="c--------" relation_orig="COORD" head_orig="7" lemma_reg="δέ" postag_reg="c--------" relation_reg="COORD" head_reg="7" tp_n="1" line_n="13" lang="grc" hand_id="160" tm_word_id=""/>
    <word id="34" form_orig="αἰσθ̣ο̣μένους" form_reg="αἰσθομένους" lemma_orig="αἰσθάνομαι" postag_orig="v-papmma-" relation_orig="SBJ" head_orig="35" lemma_reg="αἰσθάνομαι" postag_reg="v-papmma-" relation_reg="SBJ" head_reg="35" tp_n="1" line_n="13" lang="grc" hand_id="161" tm_word_id=""/>
    <word id="35" form_orig="στερῆσαι" form_reg="στερῆσαι" lemma_orig="στερέω" postag_orig="v--ana---" relation_orig="OBJ_CO" head_orig="33" lemma_reg="στερέω" postag_reg="v--ana---" relation_reg="OBJ_CO" head_reg="33" tp_n="1" line_n="13" lang="grc" hand_id="162" tm_word_id=""/>
    <word id="36" form_orig="αὐτόν" form_reg="αὐτόν" lemma_orig="αὐτός" postag_orig="p-s---ma-" relation_orig="OBJ" head_orig="35" lemma_reg="αὐτός" postag_reg="p-s---ma-" relation_reg="OBJ" head_reg="35" tp_n="1" line_n="13" lang="grc" hand_id="163" tm_word_id=""/>
    <word id="37" form_orig="·" form_reg="·" lemma_orig="punc1" postag_orig="u--------" relation_orig="AuxK" head_orig="0" lemma_reg="punc1" postag_reg="u--------" relation_reg="AuxK" head_reg="0" tp_n="1" line_n="13" lang="grc" hand_id="164" tm_word_id=""/>
  </sentence>
  <sentence id="11">
    <word id="1" form_orig="παραγενόμενος" form_reg="παραγενόμενος" lemma_orig="παραγίγνομαι" postag_orig="v-sapmmn-" relation_orig="ADV" head_orig="8" lemma_reg="παραγίγνομαι" postag_reg="v-sapmmn-" relation_reg="ADV" head_reg="8" tp_n="1" line_n="13" lang="grc" hand_id="165" tm_word_id=""/>
    <word id="2" form_orig="οὖν" form_reg="οὖν" lemma_orig="οὖν" postag_orig="d--------" relation_orig="AuxY" head_orig="8" lemma_reg="οὖν" postag_reg="d--------" relation_reg="AuxY" head_reg="8" tp_n="1" line_n="14" lang="grc" hand_id="166" tm_word_id=""/>
    <word id="3" form_orig="ὁ" form_reg="ὁ" lemma_orig="ὁ" postag_orig="l-s---mn-" relation_orig="ATR" head_orig="4" lemma_reg="ὁ" postag_reg="l-s---mn-" relation_reg="ATR" head_reg="4" tp_n="1" line_n="14" lang="grc" hand_id="167" tm_word_id=""/>
    <word id="4" form_orig="Ἀπολλοφάνης" form_reg="Ἀπολλοφάνης" lemma_orig="Ἀπολλοφάνης" postag_orig="n-s---mn-" relation_orig="SBJ" head_orig="8" lemma_reg="Ἀπολλοφάνης" postag_reg="n-s---mn-" relation_reg="SBJ" head_reg="8" tp_n="1" line_n="14" lang="grc" hand_id="168" tm_word_id=""/>
    <word id="5" form_orig="πρὸς" form_reg="πρὸς" lemma_orig="πρός" postag_orig="r--------" relation_orig="AuxP" head_orig="8" lemma_reg="πρός" postag_reg="r--------" relation_reg="AuxP" head_reg="8" tp_n="1" line_n="14" lang="grc" hand_id="169" tm_word_id=""/>
    <word id="6" form_orig="τὸν" form_reg="τὸν" lemma_orig="ὁ" postag_orig="l-s---ma-" relation_orig="ATR" head_orig="7" lemma_reg="ὁ" postag_reg="l-s---ma-" relation_reg="ATR" head_reg="7" tp_n="1" line_n="14" lang="grc" hand_id="170" tm_word_id=""/>
    <word id="7" form_orig="Μενεκλῆν" form_reg="Μενεκλῆν" lemma_orig="Μενεκλης" postag_orig="n-s---ma-" relation_orig="OBJ" head_orig="5" lemma_reg="Μενεκλης" postag_reg="n-s---ma-" relation_reg="OBJ" head_reg="5" tp_n="1" line_n="14" lang="grc" hand_id="171" tm_word_id=""/>
    <word id="8" form_orig="ἔφη̣" form_reg="ἔφη" lemma_orig="φημί" postag_orig="v3siia---" relation_orig="PRED" head_orig="0" lemma_reg="φημί" postag_reg="v3siia---" relation_reg="PRED" head_reg="0" tp_n="1" line_n="14" lang="grc" hand_id="172" tm_word_id=""/>
    <word id="9" form_orig="τ̣ά̣" form_reg="τά" lemma_orig="ὁ" postag_orig="l-p---nn-" relation_orig="ATR" head_orig="11" lemma_reg="ὁ" postag_reg="l-p---nn-" relation_reg="ATR" head_reg="11" tp_n="1" line_n="14" lang="grc" hand_id="173" tm_word_id=""/>
    <word id="10" form_orig="τε" form_reg="τε" lemma_orig="τε" postag_orig="c--------" relation_orig="AuxY" head_orig="12" lemma_reg="τε" postag_reg="c--------" relation_reg="AuxY" head_reg="12" tp_n="1" line_n="14" lang="grc" hand_id="174" tm_word_id=""/>
    <word id="11" form_orig="σώματα" form_reg="σώματα" lemma_orig="σῶμα" postag_orig="n-p---nn-" relation_orig="SBJ_CO" head_orig="12" lemma_reg="σῶμα" postag_reg="n-p---nn-" relation_reg="SBJ_CO" head_reg="12" tp_n="1" line_n="14" lang="grc" hand_id="175" tm_word_id=""/>
    <word id="12" form_orig="καὶ" form_reg="καὶ" lemma_orig="καί" postag_orig="c--------" relation_orig="COORD" head_orig="16" lemma_reg="καί" postag_reg="c--------" relation_reg="COORD" head_reg="16" tp_n="1" line_n="14" lang="grc" hand_id="176" tm_word_id=""/>
    <word id="13" form_orig="τὰ" form_reg="τὰ" lemma_orig="ὁ" postag_orig="l-p---nn-" relation_orig="ATR" head_orig="14" lemma_reg="ὁ" postag_reg="l-p---nn-" relation_reg="ATR" head_reg="14" tp_n="1" line_n="14" lang="grc" hand_id="177" tm_word_id=""/>
    <word id="14" form_orig="φορτία" form_reg="φορτία" lemma_orig="φορτίον" postag_orig="n-p---nn-" relation_orig="SBJ_CO" head_orig="12" lemma_reg="φορτίον" postag_reg="n-p---nn-" relation_reg="SBJ_CO" head_reg="12" tp_n="1" line_n="14" lang="grc" hand_id="178" tm_word_id=""/>
    <word id="15" form_orig="σὰ" form_reg="σὰ" lemma_orig="σός" postag_orig="p-p---nn-" relation_orig="PNOM" head_orig="16" lemma_reg="σός" postag_reg="p-p---nn-" relation_reg="PNOM" head_reg="16" tp_n="1" line_n="14" lang="grc" hand_id="179" tm_word_id=""/>
    <word id="16" form_orig="εἶναι" form_reg="εἶναι" lemma_orig="εἰμί" postag_orig="v--pna---" relation_orig="OBJ" head_orig="8" lemma_reg="εἰμί" postag_reg="v--pna---" relation_reg="OBJ" head_reg="8" tp_n="1" line_n="14" lang="grc" hand_id="180" tm_word_id=""/>
    <word id="17" form_orig="·" form_reg="·" lemma_orig="punc1" postag_orig="u--------" relation_orig="AuxK" head_orig="0" lemma_reg="punc1" postag_reg="u--------" relation_reg="AuxK" head_reg="0" tp_n="1" line_n="14" lang="grc" hand_id="181" tm_word_id=""/>
  </sentence>
  <sentence id="12">
    <word id="1" form_orig="διὸ" form_reg="διὸ" lemma_orig="διό" postag_orig="d-------_" relation_orig="AuxY" head_orig="3" lemma_reg="διό" postag_reg="d-------_" relation_reg="AuxY" head_reg="3" tp_n="1" line_n="15" lang="grc" hand_id="182" tm_word_id=""/>
    <word id="2" form_orig="καὶ" form_reg="καὶ" lemma_orig="καί" postag_orig="d-------_" relation_orig="AuxY" head_orig="3" lemma_reg="καί" postag_reg="d-------_" relation_reg="AuxY" head_reg="3" tp_n="1" line_n="15" lang="grc" hand_id="183" tm_word_id=""/>
    <word id="3" form_orig="ἀντελάβετ’" form_reg="ἀντελάβετ’" lemma_orig="ἀντιλαμβάνω" postag_orig="v3saim---" relation_orig="PRED" head_orig="0" lemma_reg="ἀντιλαμβάνω" postag_reg="v3saim---" relation_reg="PRED" head_reg="0" tp_n="1" line_n="15" lang="grc" hand_id="184" tm_word_id=""/>
    <word id="4" form_orig="αὐτοῦ" form_reg="αὐτοῦ" lemma_orig="αὐτός" postag_orig="p-s---mg-" relation_orig="OBJ" head_orig="3" lemma_reg="αὐτός" postag_reg="p-s---mg-" relation_reg="OBJ" head_reg="3" tp_n="1" line_n="15" lang="grc" hand_id="185" tm_word_id=""/>
    <word id="5" form_orig="ὁ" form_reg="ὁ" lemma_orig="ὁ" postag_orig="l-s---mn-" relation_orig="ATR" head_orig="6" lemma_reg="ὁ" postag_reg="l-s---mn-" relation_reg="ATR" head_reg="6" tp_n="1" line_n="15" lang="grc" hand_id="186" tm_word_id=""/>
    <word id="6" form_orig="Μενεκλῆς" form_reg="Μενεκλῆς" lemma_orig="Μενεκλῆς" postag_orig="n-s---mn-" relation_orig="SBJ" head_orig="3" lemma_reg="Μενεκλῆς" postag_reg="n-s---mn-" relation_reg="SBJ" head_reg="3" tp_n="1" line_n="15" lang="grc" hand_id="187" tm_word_id=""/>
    <word id="7" form_orig="." form_reg="." lemma_orig="punc1" postag_orig="u--------" relation_orig="AuxK" head_orig="0" lemma_reg="punc1" postag_reg="u--------" relation_reg="AuxK" head_reg="0" tp_n="1" line_n="15" lang="grc" hand_id="188" tm_word_id=""/>
  </sentence>
  <sentence id="13">
    <word id="1" form_orig="γ̣έ̣γ̣ραφα" form_reg="γέγραφα" lemma_orig="γράφω" postag_orig="v1sria---" relation_orig="PRED" head_orig="0" lemma_reg="γράφω" postag_reg="v1sria---" relation_reg="PRED" head_reg="0" tp_n="1" line_n="15" lang="grc" hand_id="189" tm_word_id=""/>
    <word id="2" form_orig="οὖν" form_reg="οὖν" lemma_orig="οὖν" postag_orig="d--------" relation_orig="AuxY" head_orig="1" lemma_reg="οὖν" postag_reg="d--------" relation_reg="AuxY" head_reg="1" tp_n="1" line_n="15" lang="grc" hand_id="190" tm_word_id=""/>
    <word id="3" form_orig="σοι" form_reg="σοι" lemma_orig="σύ" postag_orig="p2s---md-" relation_orig="OBJ" head_orig="1" lemma_reg="σύ" postag_reg="p2s---md-" relation_reg="OBJ" head_reg="1" tp_n="1" line_n="15" lang="grc" hand_id="191" tm_word_id=""/>
    <word id="4" form_orig="ὅπως" form_reg="ὅπως" lemma_orig="ὅπως" postag_orig="c--------" relation_orig="AuxC" head_orig="1" lemma_reg="ὅπως" postag_reg="c--------" relation_reg="AuxC" head_reg="1" tp_n="1" line_n="15" lang="grc" hand_id="192" tm_word_id=""/>
    <word id="5" form_orig="ἐντείληι" form_reg="ἐντείληι" lemma_orig="ἐντέλλω" postag_orig="v2sasm---" relation_orig="ADV" head_orig="4" lemma_reg="ἐντέλλω" postag_reg="v2sasm---" relation_reg="ADV" head_reg="4" tp_n="1" line_n="15" lang="grc" hand_id="193" tm_word_id=""/>
    <word id="6" form_orig="τῶι" form_reg="τῶι" lemma_orig="ὁ" postag_orig="l-s---md-" relation_orig="ATR" head_orig="7" lemma_reg="ὁ" postag_reg="l-s---md-" relation_reg="ATR" head_reg="7" tp_n="1" line_n="15" lang="grc" hand_id="194" tm_word_id=""/>
    <word id="7" form_orig="Ἀπολλοφάνει" form_reg="Ἀπολλοφάνει" lemma_orig="Ἀπολλοφάνης" postag_orig="n-s---md-" relation_orig="OBJ" head_orig="5" lemma_reg="Ἀπολλοφάνης" postag_reg="n-s---md-" relation_reg="OBJ" head_reg="5" tp_n="1" line_n="15" lang="grc" hand_id="195" tm_word_id=""/>
    <word id="8" form_orig="μηθὲν" form_reg="μηθὲν" lemma_orig="μηδείς" postag_orig="p-s---na-" relation_orig="OBJ" head_orig="13" lemma_reg="μηδείς" postag_reg="p-s---na-" relation_reg="OBJ" head_reg="13" tp_n="1" line_n="16" lang="grc" hand_id="196" tm_word_id=""/>
    <word id="9" form_orig="εἰς" form_reg="εἰς" lemma_orig="εἰς" postag_orig="r--------" relation_orig="AuxP" head_orig="13" lemma_reg="εἰς" postag_reg="r--------" relation_reg="AuxP" head_reg="13" tp_n="1" line_n="16" lang="grc" hand_id="197" tm_word_id=""/>
    <word id="10" form_orig="τὸ" form_reg="τὸ" lemma_orig="ὁ" postag_orig="l-s---na-" relation_orig="ATR" head_orig="12" lemma_reg="ὁ" postag_reg="l-s---na-" relation_reg="ATR" head_reg="12" tp_n="1" line_n="16" lang="grc" hand_id="198" tm_word_id=""/>
    <word id="11" form_orig="σὸν" form_reg="σὸν" lemma_orig="σός" postag_orig="a-s---na-" relation_orig="ATR" head_orig="12" lemma_reg="σός" postag_reg="a-s---na-" relation_reg="ATR" head_reg="12" tp_n="1" line_n="16" lang="grc" hand_id="199" tm_word_id=""/>
    <word id="12" form_orig="ὄνομα" form_reg="ὄνομα" lemma_orig="ὄνομα" postag_orig="n-s---na-" relation_orig="ADV" head_orig="9" lemma_reg="ὄνομα" postag_reg="n-s---na-" relation_reg="ADV" head_reg="9" tp_n="1" line_n="16" lang="grc" hand_id="200" tm_word_id=""/>
    <word id="13" form_orig="ἀπογράφεσθαι" form_reg="ἀπογράφεσθαι" lemma_orig="ἀπογράφω" postag_orig="v--pne---" relation_orig="OBJ" head_orig="5" lemma_reg="ἀπογράφω" postag_reg="v--pne---" relation_reg="OBJ" head_reg="5" tp_n="1" line_n="16" lang="grc" hand_id="201" tm_word_id=""/>
    <word id="14" form_orig="," form_reg="," lemma_orig="punc1" postag_orig="u--------" relation_orig="AuxX" head_orig="5" lemma_reg="punc1" postag_reg="u--------" relation_reg="AuxX" head_reg="5" tp_n="1" line_n="16" lang="grc" hand_id="202" tm_word_id=""/>
    <word id="15" form_orig="ἀ̣[λ]λ̣ʼ" form_reg="ἀλλʼ" lemma_orig="ἀλλά" postag_orig="d-------_" relation_orig="AuxZ" head_orig="18" lemma_reg="ἀλλά" postag_reg="d-------_" relation_reg="AuxZ" head_reg="18" tp_n="1" line_n="16" lang="grc" hand_id="203" tm_word_id=""/>
    <word id="16" form_orig="εἴ" form_reg="εἴ" lemma_orig="εἰ" postag_orig="c--------" relation_orig="AuxC" head_orig="5" lemma_reg="εἰ" postag_reg="c--------" relation_reg="AuxC" head_reg="5" tp_n="1" line_n="16" lang="grc" hand_id="204" tm_word_id=""/>
    <word id="17" form_orig="σοι" form_reg="σοι" lemma_orig="σύ" postag_orig="p2s---md-" relation_orig="OBJ" head_orig="18" lemma_reg="σύ" postag_reg="p2s---md-" relation_reg="OBJ" head_reg="18" tp_n="1" line_n="16" lang="grc" hand_id="205" tm_word_id=""/>
    <word id="18" form_orig="δοκεῖ" form_reg="δοκεῖ" lemma_orig="δοκέω" postag_orig="v3spia---" relation_orig="ADV" head_orig="16" lemma_reg="δοκέω" postag_reg="v3spia---" relation_reg="ADV" head_reg="16" tp_n="1" line_n="16" lang="grc" hand_id="206" tm_word_id=""/>
    <word id="19" form_orig="χρήσιμον" form_reg="χρήσιμον" lemma_orig="χρήσιμος" postag_orig="a-s---nn-" relation_orig="PNOM" head_orig="20" lemma_reg="χρήσιμος" postag_reg="a-s---nn-" relation_reg="PNOM" head_reg="20" tp_n="1" line_n="16" lang="grc" hand_id="207" tm_word_id=""/>
    <word id="20" form_orig="εἶναι" form_reg="εἶναι" lemma_orig="εἰμί" postag_orig="v--pna---" relation_orig="SBJ" head_orig="18" lemma_reg="εἰμί" postag_reg="v--pna---" relation_reg="SBJ" head_reg="18" tp_n="1" line_n="16" lang="grc" hand_id="208" tm_word_id=""/>
    <word id="21" form_orig="." form_reg="." lemma_orig="punc1" postag_orig="u--------" relation_orig="AuxK" head_orig="0" lemma_reg="punc1" postag_reg="u--------" relation_reg="AuxK" head_reg="0" tp_n="1" line_n="16" lang="grc" hand_id="209" tm_word_id=""/>
  </sentence>
  <sentence id="14">
    <word id="1" form_orig="γίνωσκε" form_reg="γίνωσκε" lemma_orig="γιγνώσκω" postag_orig="v2spma---" relation_orig="PRED_CO" head_orig="2" lemma_reg="γιγνώσκω" postag_reg="v2spma---" relation_reg="PRED_CO" head_reg="2" tp_n="1" line_n="16" lang="grc" hand_id="210" tm_word_id=""/>
    <word id="2" form_orig="δὲ" form_reg="δὲ" lemma_orig="δέ" postag_orig="c--------" relation_orig="COORD" head_orig="0" lemma_reg="δέ" postag_reg="c--------" relation_reg="COORD" head_reg="0" tp_n="1" line_n="16" lang="grc" hand_id="211" tm_word_id=""/>
    <word id="3" form_orig="καὶ" form_reg="καὶ" lemma_orig="καί" postag_orig="d-------_" relation_orig="AuxZ" head_orig="4" lemma_reg="καί" postag_reg="d-------_" relation_reg="AuxZ" head_reg="4" tp_n="1" line_n="17" lang="grc" hand_id="212" tm_word_id=""/>
    <word id="4" form_orig="ἡμᾶς" form_reg="ἡμᾶς" lemma_orig="ἐγώ" postag_orig="p1p---ma-" relation_orig="OBJ" head_orig="1" lemma_reg="ἐγώ" postag_reg="p1p---ma-" relation_reg="OBJ" head_reg="1" tp_n="1" line_n="17" lang="grc" hand_id="213" tm_word_id=""/>
    <word id="5" form_orig="πολλὰ" form_reg="πολλὰ" lemma_orig="πολύς" postag_orig="d-------_" relation_orig="ADV" head_orig="6" lemma_reg="πολύς" postag_reg="d-------_" relation_reg="ADV" head_reg="6" tp_n="1" line_n="17" lang="grc" hand_id="214" tm_word_id=""/>
    <word id="6" form_orig="κακοπαθήσαντας" form_reg="κακοπαθήσαντας" lemma_orig="κακοπαθέω" postag_orig="v-papama-" relation_orig="OCOMP_CO" head_orig="7" lemma_reg="κακοπαθέω" postag_reg="v-papama-" relation_reg="OCOMP_CO" head_reg="7" tp_n="1" line_n="17" lang="grc" hand_id="215" tm_word_id=""/>
    <word id="7" form_orig="καὶ" form_reg="καὶ" lemma_orig="καί" postag_orig="c--------" relation_orig="COORD" head_orig="1" lemma_reg="καί" postag_reg="c--------" relation_reg="COORD" head_reg="1" tp_n="1" line_n="17" lang="grc" hand_id="216" tm_word_id=""/>
    <word id="8" form_orig="μ̣ό̣[γ]ι̣ς̣" form_reg="μόγις" lemma_orig="μόγις" postag_orig="d--------" relation_orig="ADV" head_orig="9" lemma_reg="μόγις" postag_reg="d--------" relation_reg="ADV" head_reg="9" tp_n="1" line_n="17" lang="grc" hand_id="217" tm_word_id=""/>
    <word id="9" form_orig="καταχωρισθέντας" form_reg="καταχωρισθέντας" lemma_orig="καταχωρίζω" postag_orig="v-pappma-" relation_orig="OCOMP_CO" head_orig="7" lemma_reg="καταχωρίζω" postag_reg="v-pappma-" relation_reg="OCOMP_CO" head_reg="7" tp_n="1" line_n="17" lang="grc" hand_id="218" tm_word_id=""/>
    <word id="10" form_orig="ἐν" form_reg="ἐν" lemma_orig="ἐν" postag_orig="r--------" relation_orig="AuxP" head_orig="9" lemma_reg="ἐν" postag_reg="r--------" relation_reg="AuxP" head_reg="9" tp_n="1" line_n="17" lang="grc" hand_id="219" tm_word_id=""/>
    <word id="11" form_orig="τῶι" form_reg="τῶι" lemma_orig="ὁ" postag_orig="l-s---md-" relation_orig="ATR" head_orig="13" lemma_reg="ὁ" postag_reg="l-s---md-" relation_reg="ATR" head_reg="13" tp_n="1" line_n="17" lang="grc" hand_id="220" tm_word_id=""/>
    <word id="12" form_orig="Δαισίωι" form_reg="Δαισίωι" lemma_orig="Δαίσιος" postag_orig="n-s---md-" relation_orig="ADV" head_orig="10" lemma_reg="Δαίσιος" postag_reg="n-s---md-" relation_reg="ADV" head_reg="10" tp_n="1" line_n="17" lang="grc" hand_id="221" tm_word_id=""/>
    <word id="13" form_orig="μηνὶ" form_reg="μηνὶ" lemma_orig="μείς" postag_orig="n-s---md-" relation_orig="ATR" head_orig="12" lemma_reg="μείς" postag_reg="n-s---md-" relation_reg="ATR" head_reg="12" tp_n="1" line_n="17" lang="grc" hand_id="222" tm_word_id=""/>
    <word id="14" form_orig="τοῦ" form_reg="τοῦ" lemma_orig="ὁ" postag_orig="l-s---ng-" relation_orig="ATR" head_orig="16" lemma_reg="ὁ" postag_reg="l-s---ng-" relation_reg="ATR" head_reg="16" tp_n="1" line_n="18" lang="grc" hand_id="223" tm_word_id=""/>
    <word id="15" form_orig="κθ|num:29|" form_reg="κθ|num:29|" lemma_orig="κθ" postag_orig="m-_---__-" relation_orig="ATR" head_orig="16" lemma_reg="κθ" postag_reg="m-_---__-" relation_reg="ATR" head_reg="16" tp_n="1" line_n="18" lang="grc" hand_id="224" tm_word_id=""/>
    <word id="16" form_orig="❨(ἔτους)❩" form_reg="ἔτους" lemma_orig="ἔτος" postag_orig="n-_---n_-" relation_orig="ADV" head_orig="9" lemma_reg="ἔτος" postag_reg="n-s---ng-" relation_reg="ADV" head_reg="9" tp_n="1" line_n="18" lang="grc" hand_id="225" tm_word_id=""/>
    <word id="17" form_orig="." form_reg="." lemma_orig="punc1" postag_orig="u--------" relation_orig="AuxK" head_orig="0" lemma_reg="punc1" postag_reg="u--------" relation_reg="AuxK" head_reg="0" tp_n="1" line_n="18" lang="grc" hand_id="226" tm_word_id=""/>
  </sentence>
  <sentence id="15">
    <word id="1" form_orig="Νικάνωρ" form_reg="Νικάνωρ" lemma_orig="Νικάνωρ" postag_orig="n-s---mn-" relation_orig="SBJ" head_orig="4" lemma_reg="Νικάνωρ" postag_reg="n-s---mn-" relation_reg="SBJ" head_reg="4" tp_n="1" line_n="18" lang="grc" hand_id="227" tm_word_id=""/>
    <word id="2" form_orig="μὲν" form_reg="μὲν" lemma_orig="μέν" postag_orig="d--------" relation_orig="AuxY" head_orig="4" lemma_reg="μέν" postag_reg="d--------" relation_reg="AuxY" head_reg="4" tp_n="1" line_n="18" lang="grc" hand_id="228" tm_word_id=""/>
    <word id="3" form_orig="γὰρ" form_reg="γὰρ" lemma_orig="γάρ" postag_orig="d--------" relation_orig="AuxY" head_orig="4" lemma_reg="γάρ" postag_reg="d--------" relation_reg="AuxY" head_reg="4" tp_n="1" line_n="18" lang="grc" hand_id="229" tm_word_id=""/>
    <word id="4" form_orig="κέχρηται" form_reg="κέχρηται" lemma_orig="χράω2" postag_orig="v3srie---" relation_orig="PRED" head_orig="0" lemma_reg="χράω2" postag_reg="v3srie---" relation_reg="PRED" head_reg="0" tp_n="1" line_n="18" lang="grc" hand_id="230" tm_word_id=""/>
    <word id="5" form_orig="ἡμῖν" form_reg="ἡμῖν" lemma_orig="ἐγώ" postag_orig="p1p---md-" relation_orig="OBJ" head_orig="4" lemma_reg="ἐγώ" postag_reg="p1p---md-" relation_reg="OBJ" head_reg="4" tp_n="1" line_n="18" lang="grc" hand_id="231" tm_word_id=""/>
    <word id="6" form_orig="ὡς" form_reg="ὡς" lemma_orig="ὡς" postag_orig="d-------_" relation_orig="AuxZ" head_orig="11" lemma_reg="ὡς" postag_reg="d-------_" relation_reg="AuxZ" head_reg="11" tp_n="1" line_n="18" lang="grc" hand_id="232" tm_word_id=""/>
    <word id="7" form_orig="ἂν" form_reg="ἂν" lemma_orig="ἄν1" postag_orig="d--------" relation_orig="AuxY" head_orig="11" lemma_reg="ἄν1" postag_reg="d--------" relation_reg="AuxY" head_reg="11" tp_n="1" line_n="18" lang="grc" hand_id="233" tm_word_id=""/>
    <word id="8" form_orig="εἴ" form_reg="εἴ" lemma_orig="εἰ" postag_orig="c--------" relation_orig="AuxC" head_orig="4" lemma_reg="εἰ" postag_reg="c--------" relation_reg="AuxC" head_reg="4" tp_n="1" line_n="18" lang="grc" hand_id="234" tm_word_id=""/>
    <word id="9" form_orig="τις" form_reg="τις" lemma_orig="τις" postag_orig="p-s---mn-" relation_orig="SBJ" head_orig="11" lemma_reg="τις" postag_reg="p-s---mn-" relation_reg="SBJ" head_reg="11" tp_n="1" line_n="18" lang="grc" hand_id="235" tm_word_id=""/>
    <word id="10" form_orig="ἐχθρῶι" form_reg="ἐχθρῶι" lemma_orig="ἐχθρός" postag_orig="a-s---md-" relation_orig="OBJ" head_orig="11" lemma_reg="ἐχθρός" postag_reg="a-s---md-" relation_reg="OBJ" head_reg="11" tp_n="1" line_n="18" lang="grc" hand_id="236" tm_word_id=""/>
    <word id="11" form_orig="χρήσαιτο" form_reg="χρήσαιτο" lemma_orig="χράω2" postag_orig="v3saom---" relation_orig="ADV" head_orig="8" lemma_reg="χράω2" postag_reg="v3saom---" relation_reg="ADV" head_reg="8" tp_n="1" line_n="18" lang="grc" hand_id="237" tm_word_id=""/>
    <word id="12" form_orig="." form_reg="." lemma_orig="punc1" postag_orig="u--------" relation_orig="AuxK" head_orig="0" lemma_reg="punc1" postag_reg="u--------" relation_reg="AuxK" head_reg="0" tp_n="1" line_n="18" lang="grc" hand_id="238" tm_word_id=""/>
  </sentence>
  <sentence id="16">
    <word id="1" form_orig="καλῶς" form_reg="καλῶς" lemma_orig="καλός" postag_orig="d-------_" relation_orig="ADV" head_orig="4" lemma_reg="καλός" postag_reg="d-------_" relation_reg="ADV" head_reg="4" tp_n="1" line_n="19" lang="grc" hand_id="239" tm_word_id=""/>
    <word id="2" form_orig="δʼ" form_reg="δʼ" lemma_orig="δέ" postag_orig="c--------" relation_orig="COORD" head_orig="0" lemma_reg="δέ" postag_reg="c--------" relation_reg="COORD" head_reg="0" tp_n="1" line_n="19" lang="grc" hand_id="240" tm_word_id=""/>
    <word id="3" form_orig="ἂν" form_reg="ἂν" lemma_orig="ἄν1" postag_orig="d--------" relation_orig="AuxY" head_orig="4" lemma_reg="ἄν1" postag_reg="d--------" relation_reg="AuxY" head_reg="4" tp_n="1" line_n="19" lang="grc" hand_id="241" tm_word_id=""/>
    <word id="4" form_orig="ποιοῖς" form_reg="ποιοῖς" lemma_orig="ποιέω" postag_orig="v2spoa---" relation_orig="PRED_CO" head_orig="2" lemma_reg="ποιέω" postag_reg="v2spoa---" relation_reg="PRED_CO" head_reg="2" tp_n="1" line_n="19" lang="grc" hand_id="242" tm_word_id=""/>
    <word id="5" form_orig="καὶ" form_reg="καὶ" lemma_orig="καί" postag_orig="d-------_" relation_orig="AuxZ" head_orig="6" lemma_reg="καί" postag_reg="d-------_" relation_reg="AuxZ" head_reg="6" tp_n="1" line_n="19" lang="grc" hand_id="243" tm_word_id=""/>
    <word id="6" form_orig="σὺ" form_reg="σὺ" lemma_orig="σύ" postag_orig="p2s---mn-" relation_orig="" head_orig="" lemma_reg="σύ" postag_reg="p2s---mn-" relation_reg="SBJ" head_reg="7" tp_n="1" line_n="19" lang="grc" hand_id="244" tm_word_id=""/>
    <word id="7" form_orig="ἐπι[μ]ελόμεν[ος]" form_reg="ἐπιμελόμενος" lemma_orig="ἐπιμελέομαι" postag_orig="v-sppem--" relation_orig="OBJ" head_orig="" lemma_reg="ἐπιμελέομαι" postag_reg="v-sppemn-" relation_reg="OBJ" head_reg="4" tp_n="1" line_n="19" lang="grc" hand_id="245" tm_word_id=""/>
    <word id="8" form_orig="σ̣α̣[υτο]ῦ" form_reg="σαυτοῦ" lemma_orig="σαυτοῦ" postag_orig="p-s---mg-" relation_orig="OBJ" head_orig="" lemma_reg="σαυτοῦ" postag_reg="p-s---mg-" relation_reg="OBJ" head_reg="7" tp_n="1" line_n="19" lang="grc" hand_id="246" tm_word_id=""/>
    <word id="9" form_orig="ὅπως" form_reg="ὅπως" lemma_orig="ὅπως" postag_orig="c--------" relation_orig="" head_orig="" lemma_reg="ὅπως" postag_reg="c--------" relation_reg="AuxC" head_reg="7" tp_n="1" line_n="19" lang="grc" hand_id="247" tm_word_id=""/>
    <word id="10" form_orig="ὑγιαίνηις" form_reg="ὑγιαίνηις" lemma_orig="ὑγιαίνω" postag_orig="v2spsa---" relation_orig="ADV" head_orig="9" lemma_reg="ὑγιαίνω" postag_reg="v2spsa---" relation_reg="ADV" head_reg="9" tp_n="1" line_n="19" lang="grc" hand_id="248" tm_word_id=""/>
    <word id="11" form_orig="." form_reg="." lemma_orig="punc1" postag_orig="u--------" relation_orig="AuxK" head_orig="0" lemma_reg="punc1" postag_reg="u--------" relation_reg="AuxK" head_reg="0" tp_n="1" line_n="19" lang="grc" hand_id="249" tm_word_id=""/>
  </sentence>
  <sentence id="17">
    <word id="1" form_orig="ἔρρωσο" form_reg="ἔρρωσο" lemma_orig="ῥώννυμι" postag_orig="v2srme---" relation_orig="PRED" head_orig="0" lemma_reg="ῥώννυμι" postag_reg="v2srme---" relation_reg="PRED" head_reg="0" tp_n="1" line_n="20" lang="grc" hand_id="250" tm_word_id=""/>
    <word id="2" form_orig="." form_reg="." lemma_orig="punc1" postag_orig="u--------" relation_orig="AuxK" head_orig="0" lemma_reg="punc1" postag_reg="u--------" relation_reg="AuxK" head_reg="0" tp_n="1" line_n="20" lang="grc" hand_id="251" tm_word_id=""/>
  </sentence>
  <sentence id="18">
    <word id="1" form_orig="Ἡρακλείτου" form_reg="Ἡρακλείτου" lemma_orig="Ἡράκλειτος" postag_orig="n-s---mg-" relation_orig="ATR" head_orig="3" lemma_reg="Ἡράκλειτος" postag_reg="n-s---mg-" relation_reg="ATR" head_reg="3" tp_n="2" line_n="21" lang="grc" hand_id="252" tm_word_id=""/>
    <word id="2" form_orig="." form_reg="." lemma_orig="punc1" postag_orig="u--------" relation_orig="AuxK" head_orig="0" lemma_reg="punc1" postag_reg="u--------" relation_reg="AuxK" head_reg="0" tp_n="2" line_n="21" lang="grc" hand_id="253" tm_word_id=""/>
    <word id="3" form_orig="[0]" form_reg="[0]" lemma_orig="" postag_orig="" relation_orig="ExD" head_orig="0" lemma_reg="" postag_reg="" relation_reg="ExD" head_reg="0" insertion_id="0000e" artificial="elliptic" tp_n="" line_n="None" lang="None" hand_id="254" tm_word_id=""/>
  </sentence>
  <sentence id="19">
    <word id="1" form_orig="|vac:?|" form_reg="|vac:?|" lemma_orig="" postag_orig="" relation_orig="" head_orig="" lemma_reg="" postag_reg="" relation_reg="" head_reg="" tp_n="2" line_n="21" lang="grc" hand_id="255" tm_word_id=""/>
    <word id="2" form_orig="Ζήνωνι" form_reg="Ζήνωνι" lemma_orig="Ζήνων" postag_orig="n-s---md-" relation_orig="OBJ" head_orig="4" lemma_reg="Ζήνων" postag_reg="n-s---md-" relation_reg="OBJ" head_reg="4" tp_n="2" line_n="21" lang="grc" hand_id="256" tm_word_id=""/>
    <word id="3" form_orig="." form_reg="." lemma_orig="punc1" postag_orig="u--------" relation_orig="AuxK" head_orig="0" lemma_reg="punc1" postag_reg="u--------" relation_reg="AuxK" head_reg="0" tp_n="2" line_n="21" lang="grc" hand_id="257" tm_word_id=""/>
    <word id="4" form_orig="[0]" form_reg="[0]" lemma_orig="" postag_orig="" relation_orig="ExD" head_orig="0" lemma_reg="" postag_reg="" relation_reg="ExD" head_reg="0" insertion_id="0000e" artificial="elliptic" tp_n="" line_n="None" lang="None" hand_id="258" tm_word_id=""/>
  </sentence>
</treebank>
