<treebank xmlns:saxon="http://saxon.sf.net/" text_id="21497" format="aldt" version="1.5" direction="ltr" xml:lang="grc">
  <annotator name="Marja Vierros" address="vierrosm@gmail.com" role="approved" date="2020-06-12" layer="orig"/>
  <annotator name="Marja Vierros" address="vierrosm@gmail.com" role="approved" date="2020-06-12" layer="reg"/>
  <annotator name="Marja Vierros" address="vierrosm@gmail.com" role="annotated" date="2020-06-12" layer="reg"/>
  <annotator name="Marja Vierros" address="vierrosm@gmail.com" role="annotated" date="2020-06-12" layer="orig"/>
  <annotator name="Jamie Vesterinen" address="jamie.vesterinen@gmail.com" role="annotated" date="2020-06-02" layer="reg"/>
  <annotator name="Jamie Vesterinen" address="jamie.vesterinen@gmail.com" role="annotated" date="2020-06-02" layer="orig"/>
  <document_meta name="p.adl.G15.xml" series_name="p.adl" series_type="documentary" tm_id="15" hgv_id="15" date_not_before="-100" date_not_after="-100" place_name="Pathyris (?)"/>
  <hand_meta name="m1" id="1">
    <text_type hypercategory="LAW" category="Contract" subcategory="Loan"/>
    <person pg_id="155" tm_id="73" role="author" handwriting="" honorific_epithet="" ethnic_label="" occupation="agoranomos (under Paniskos)" domicile="" age="" education="professional" name="Hermias" gender="1" uncertain=""/>
    <person pg_id="156" tm_id="70" role="official" handwriting="" honorific_epithet="" ethnic_label="" occupation="agoranomos" domicile="" age="" education="" name="Paniskos" gender="1" uncertain=""/>
    <person pg_id="214" tm_id="" role="writer" handwriting="" honorific_epithet="" ethnic_label="" occupation="" domicile="" age="" education="" name="" gender="" uncertain="1"/>
  </hand_meta>
  <sentence id="1">
    <word id="1" form_orig="[ἔτους]" form_reg="ἔτους" lemma_orig="" postag_orig="" relation_orig="nil" head_orig="" lemma_reg="ἔτος" postag_reg="n-s---ng-" relation_reg="ADV" head_reg="13" tp_n="1" line_n="1" lang="grc" hand_id="1" tm_word_id=""/>
    <word id="2" form_orig="[ιε|num:15|]" form_reg="ιε|num:15|" lemma_orig="" postag_orig="" relation_orig="nil" head_orig="" lemma_reg="ιε" postag_reg="m-p---__-" relation_reg="ATR" head_reg="1" tp_n="1" line_n="1" lang="grc" hand_id="2" tm_word_id=""/>
    <word id="3" form_orig="|gap:7|" form_reg="|gap:7|" lemma_orig="" postag_orig="" relation_orig="nil" head_orig="" lemma_reg="" postag_reg="" relation_reg="" head_reg="" tp_n="1" line_n="1" lang="grc" hand_id="3" tm_word_id=""/>
    <word id="4" form_orig="[ἐν]" form_reg="ἐν" lemma_orig="" postag_orig="" relation_orig="nil" head_orig="" lemma_reg="ἐν" postag_reg="r--------" relation_reg="AuxP" head_reg="13" tp_n="1" line_n="1" lang="grc" hand_id="4" tm_word_id=""/>
    <word id="5" form_orig="[Παθύρει]" form_reg="Παθύρει" lemma_orig="" postag_orig="" relation_orig="nil" head_orig="" lemma_reg="Παθυρις" postag_reg="n-s---_d-" relation_reg="ADV" head_reg="4" tp_n="1" line_n="1" lang="grc" hand_id="5" tm_word_id=""/>
    <word id="6" form_orig="[ἐφʼ]" form_reg="ἐφʼ" lemma_orig="" postag_orig="" relation_orig="nil" head_orig="" lemma_reg="ἐπί" postag_reg="r--------" relation_reg="AuxP" head_reg="13" tp_n="1" line_n="1" lang="grc" hand_id="6" tm_word_id=""/>
    <word id="7" form_orig="[Ἑρμίου]" form_reg="Ἑρμίου" lemma_orig="" postag_orig="" relation_orig="nil" head_orig="" lemma_reg="Ἑρμίας" postag_reg="n-s---mg-" relation_reg="ADV" head_reg="6" tp_n="1" line_n="1" lang="grc" hand_id="7" tm_word_id=""/>
    <word id="8" form_orig="[τοῦ]" form_reg="τοῦ" lemma_orig="" postag_orig="" relation_orig="nil" head_orig="" lemma_reg="ὁ" postag_reg="l-s---mg-" relation_reg="ATR" head_reg="11" tp_n="1" line_n="1" lang="grc" hand_id="8" tm_word_id=""/>
    <word id="9" form_orig="[πα]ρ̣[ὰ]" form_reg="παρὰ" lemma_orig="" postag_orig="" relation_orig="nil" head_orig="" lemma_reg="παρά" postag_reg="r--------" relation_reg="AuxP" head_reg="11" tp_n="1" line_n="2" lang="grc" hand_id="9" tm_word_id=""/>
    <word id="10" form_orig="[Πανίσκου]" form_reg="Πανίσκου" lemma_orig="" postag_orig="" relation_orig="nil" head_orig="" lemma_reg="Πανίσκος" postag_reg="n-s---mg-" relation_reg="ATR" head_reg="9" tp_n="1" line_n="2" lang="grc" hand_id="10" tm_word_id=""/>
    <word id="11" form_orig="[ἀγο]ρ̣[ανόμου]" form_reg="ἀγορανόμου" lemma_orig="" postag_orig="" relation_orig="nil" head_orig="" lemma_reg="ἀγορανόμος" postag_reg="n-s---mg-" relation_reg="ATR" head_reg="7" tp_n="1" line_n="2" lang="grc" hand_id="11" tm_word_id=""/>
    <word id="12" form_orig="[.]" form_reg="." lemma_orig="punc1" postag_orig="u--------" relation_orig="AuxK" head_orig="0" lemma_reg="punc1" postag_reg="u--------" relation_reg="AuxK" head_reg="0" tp_n="1" line_n="2" lang="grc" hand_id="12" tm_word_id=""/>
    <word id="13" form_orig="ἐγράφη" form_reg="ἐγράφη" lemma_orig="" postag_orig="" relation_orig="" head_orig="" lemma_reg="" postag_reg="" relation_reg="PRED" head_reg="0" insertion_id="0011e" artificial="elliptic" tp_n="" line_n="None" lang="None" hand_id="13" tm_word_id=""/>
  </sentence>
  <sentence id="2">
    <word id="1" form_orig="[ἐδάνεισεν]" form_reg="ἐδάνεισεν" lemma_orig="" postag_orig="" relation_orig="PRED_CO" head_orig="40" lemma_reg="δανείζω" postag_reg="v3saia---" relation_reg="PRED_CO" head_reg="40" tp_n="1" line_n="2" lang="grc" hand_id="14" tm_word_id=""/>
    <word id="2" form_orig="[Ὧρος]" form_reg="Ὧρος" lemma_orig="" postag_orig="" relation_orig="SBJ" head_orig="1" lemma_reg="Ὡρος" postag_reg="n-s---mn-" relation_reg="SBJ" head_reg="1" tp_n="1" line_n="2" lang="grc" hand_id="15" tm_word_id=""/>
    <word id="3" form_orig="Ὥ̣ρου" form_reg="Ὥρου" lemma_orig="Ὡρος" postag_orig="n-s---mg-" relation_orig="ATR" head_orig="2" lemma_reg="Ὡρος" postag_reg="n-s---mg-" relation_reg="ATR" head_reg="2" tp_n="1" line_n="3" lang="grc" hand_id="16" tm_word_id=""/>
    <word id="4" form_orig="Ὥρωι" form_reg="Ὥρωι" lemma_orig="Ὡρος" postag_orig="n-s---md-" relation_orig="OBJ" head_orig="1" lemma_reg="Ὡρος" postag_reg="n-s---md-" relation_reg="OBJ" head_reg="1" tp_n="1" line_n="3" lang="grc" hand_id="17" tm_word_id=""/>
    <word id="5" form_orig="∼Νεχουτωι∽" form_reg="Νεχούτου" lemma_orig="Νεχουτης" postag_orig="n-s---md-" relation_orig="ATR" head_orig="4" lemma_reg="Νεχουτης" postag_reg="n-s---mg-" relation_reg="ATR" head_reg="4" tp_n="1" line_n="3" lang="grc" hand_id="18" tm_word_id=""/>
    <word id="6" form_orig="ὡς" form_reg="ὡς" lemma_orig="ὡς" postag_orig="d-------_" relation_orig="AuxZ" head_orig="7" lemma_reg="ὡς" postag_reg="d-------_" relation_reg="AuxZ" head_reg="7" tp_n="1" line_n="3" lang="grc" hand_id="19" tm_word_id=""/>
    <word id="7" form_orig="❨(ἐτῶν)❩" form_reg="ἐτῶν" lemma_orig="ἔτος" postag_orig="n-_---n_-" relation_orig="ATR" head_orig="4" lemma_reg="ἔτος" postag_reg="n-p---ng-" relation_reg="ATR" head_reg="4" tp_n="1" line_n="3" lang="grc" hand_id="20" tm_word_id=""/>
    <word id="8" form_orig="ν̣|num:50|" form_reg="ν|num:50|" lemma_orig="ν" postag_orig="m-p---__-" relation_orig="ATR" head_orig="7" lemma_reg="ν" postag_reg="m-p---__-" relation_reg="ATR" head_reg="7" tp_n="1" line_n="3" lang="grc" hand_id="21" tm_word_id=""/>
    <word id="9" form_orig="[μέσος]" form_reg="μέσος" lemma_orig="" postag_orig="" relation_orig="" head_orig="" lemma_reg="μέσος" postag_reg="a-s---mn-" relation_reg="PNOM" head_reg="67" tp_n="1" line_n="3" lang="grc" hand_id="22" tm_word_id=""/>
    <word id="10" form_orig="[μελίχρως]" form_reg="μελίχρως" lemma_orig="" postag_orig="" relation_orig="" head_orig="" lemma_reg="μελίχρως" postag_reg="n-s---mn-" relation_reg="PNOM" head_reg="67" tp_n="1" line_n="3" lang="grc" hand_id="23" tm_word_id=""/>
    <word id="11" form_orig="ὑπ̣ο̣κλαστὸς" form_reg="ὑποκλαστὸς" lemma_orig="ὑπόκλαστος" postag_orig="a-s---mn_" relation_orig="PNOM" head_orig="67" lemma_reg="ὑπόκλαστος" postag_reg="a-s---mn_" relation_reg="PNOM" head_reg="67" tp_n="1" line_n="4" lang="grc" hand_id="24" tm_word_id=""/>
    <word id="12" form_orig="ἀναφάλακρος" form_reg="ἀναφάλακρος" lemma_orig="ἀναφάλακρος" postag_orig="a-s---mn-" relation_orig="PNOM" head_orig="67" lemma_reg="ἀναφάλακρος" postag_reg="a-s---mn-" relation_reg="PNOM" head_reg="67" tp_n="1" line_n="4" lang="grc" hand_id="25" tm_word_id=""/>
    <word id="13" form_orig="μακροπρόσωπος" form_reg="μακροπρόσωπος" lemma_orig="μακροπρόσωπος" postag_orig="a-s---mn-" relation_orig="PNOM" head_orig="67" lemma_reg="μακροπρόσωπος" postag_reg="a-s---mn-" relation_reg="PNOM" head_reg="67" tp_n="1" line_n="4" lang="grc" hand_id="26" tm_word_id=""/>
    <word id="14" form_orig="εὐθύριν" form_reg="εὐθύριν" lemma_orig="εὐθύρριν" postag_orig="n-s---mn-" relation_orig="PNOM" head_orig="67" lemma_reg="εὐθύρριν" postag_reg="n-s---mn-" relation_reg="PNOM" head_reg="67" tp_n="1" line_n="5" lang="grc" hand_id="27" tm_word_id=""/>
    <word id="15" form_orig="∼ἦς∽" form_reg="οὖς" lemma_orig="οὖς" postag_orig="n-s---_n-" relation_orig="SBJ" head_orig="69" lemma_reg="οὖς" postag_reg="n-s---nn-" relation_reg="SBJ" head_reg="69" tp_n="1" line_n="5" lang="grc" hand_id="28" tm_word_id=""/>
    <word id="16" form_orig="ἀριστερὸν" form_reg="ἀριστερὸν" lemma_orig="ἀριστερός" postag_orig="a-s---nn-" relation_orig="ATR" head_orig="15" lemma_reg="ἀριστερός" postag_reg="a-s---nn-" relation_reg="ATR" head_reg="15" tp_n="1" line_n="5" lang="grc" hand_id="29" tm_word_id=""/>
    <word id="17" form_orig="τετρημένον" form_reg="τετρημένον" lemma_orig="τετραίνω" postag_orig="v-srpenn-" relation_orig="PNOM" head_orig="69" lemma_reg="τετραίνω" postag_reg="v-srpenn-" relation_reg="PNOM" head_reg="69" tp_n="1" line_n="5" lang="grc" hand_id="30" tm_word_id=""/>
    <word id="18" form_orig="πυροῦ̣" form_reg="πυροῦ" lemma_orig="πυρός" postag_orig="n-s---mg-" relation_orig="ATR" head_orig="19" lemma_reg="πυρός" postag_reg="n-s---mg-" relation_reg="ATR" head_reg="19" tp_n="1" line_n="5" lang="grc" hand_id="31" tm_word_id=""/>
    <word id="19" form_orig="ἀρτάβας" form_reg="ἀρτάβας" lemma_orig="ἀρτάβη" postag_orig="n-p---fa-" relation_orig="OBJ" head_orig="1" lemma_reg="ἀρτάβη" postag_reg="n-p---fa-" relation_reg="OBJ" head_reg="1" tp_n="1" line_n="5" lang="grc" hand_id="32" tm_word_id=""/>
    <word id="20" form_orig="τεσσαράκοντα" form_reg="τεσσαράκοντα" lemma_orig="τεσσαράκοντα" postag_orig="m-p---__-" relation_orig="ATR_CO" head_orig="70" lemma_reg="τεσσαράκοντα" postag_reg="m-p---__-" relation_reg="ATR_CO" head_reg="70" tp_n="1" line_n="6" lang="grc" hand_id="33" tm_word_id=""/>
    <word id="21" form_orig="ἓξ|num:46|" form_reg="ἓξ|num:46|" lemma_orig="ἕξ" postag_orig="m-p---__-" relation_orig="ATR_CO" head_orig="70" lemma_reg="ἕξ" postag_reg="m-p---__-" relation_reg="ATR_CO" head_reg="70" tp_n="1" line_n="6" lang="grc" hand_id="34" tm_word_id=""/>
    <word id="22" form_orig="κ̣ριθῆς" form_reg="κριθῆς" lemma_orig="κριθή" postag_orig="n-s---fg-" relation_orig="ATR" head_orig="19" lemma_reg="κριθή" postag_reg="n-s---fg-" relation_reg="ATR" head_reg="19" tp_n="1" line_n="6" lang="grc" hand_id="35" tm_word_id=""/>
    <word id="23" form_orig="ἑξήκοντα" form_reg="ἑξήκοντα" lemma_orig="ἑξήκοντα" postag_orig="m-p---__-" relation_orig="ATR_CO" head_orig="71" lemma_reg="ἑξήκοντα" postag_reg="m-p---__-" relation_reg="ATR_CO" head_reg="71" tp_n="1" line_n="6" lang="grc" hand_id="36" tm_word_id=""/>
    <word id="24" form_orig="∼ἐνέα∽|num:69|" form_reg="ἐννέα|num:69|" lemma_orig="ἐννέα" postag_orig="m-p---__-" relation_orig="ATR_CO" head_orig="71" lemma_reg="ἐννέα" postag_reg="m-p---__-" relation_reg="ATR_CO" head_reg="71" tp_n="1" line_n="6" lang="grc" hand_id="37" tm_word_id=""/>
    <word id="25" form_orig="," form_reg="," lemma_orig="punc1" postag_orig="u--------" relation_orig="AuxX" head_orig="27" lemma_reg="punc1" postag_reg="u--------" relation_reg="AuxX" head_reg="27" tp_n="1" line_n="6" lang="grc" hand_id="38" tm_word_id=""/>
    <word id="26" form_orig="ἴσο̣υ[ς]" form_reg="ἴσους" lemma_orig="ἴσος" postag_orig="a-_---m__" relation_orig="ATR" head_orig="27" lemma_reg="ἴσος" postag_reg="a-p---ma-" relation_reg="ATR" head_reg="27" tp_n="1" line_n="6" lang="grc" hand_id="39" tm_word_id=""/>
    <word id="27" form_orig="ἀτό̣κους" form_reg="ἀτόκους" lemma_orig="ἄτοκος" postag_orig="a-p---fa-" relation_orig="ATR" head_orig="19" lemma_reg="ἄτοκος" postag_reg="a-p---fa-" relation_reg="ATR" head_reg="19" tp_n="1" line_n="7" lang="grc" hand_id="40" tm_word_id=""/>
    <word id="28" form_orig="," form_reg="," lemma_orig="punc1" postag_orig="u--------" relation_orig="AuxX" head_orig="31" lemma_reg="punc1" postag_reg="u--------" relation_reg="AuxX" head_reg="31" tp_n="1" line_n="7" lang="grc" hand_id="41" tm_word_id=""/>
    <word id="29" form_orig="ὧν" form_reg="ὧν" lemma_orig="ὅς" postag_orig="p-p---fg-" relation_orig="ATR" head_orig="30" lemma_reg="ὅς" postag_reg="p-p---fg-" relation_reg="ATR" head_reg="30" tp_n="1" line_n="7" lang="grc" hand_id="42" tm_word_id=""/>
    <word id="30" form_orig="ἀπόδ̣ο̣σιν" form_reg="ἀπόδοσιν" lemma_orig="ἀπόδοσις" postag_orig="n-s---fa-" relation_orig="OBJ" head_orig="31" lemma_reg="ἀπόδοσις" postag_reg="n-s---fa-" relation_reg="OBJ" head_reg="31" tp_n="1" line_n="7" lang="grc" hand_id="43" tm_word_id=""/>
    <word id="31" form_orig="&lt;ποιησάτω&gt;" form_reg="ποιησάτω" lemma_orig="" postag_orig="" relation_orig="ATR" head_orig="19" lemma_reg="ποιέω" postag_reg="v3sama---" relation_reg="ATR" head_reg="19" tp_n="1" line_n="7" lang="grc" hand_id="44" tm_word_id=""/>
    <word id="32" form_orig="ἐν" form_reg="ἐν" lemma_orig="ἐν" postag_orig="r--------" relation_orig="AuxP" head_orig="31" lemma_reg="ἐν" postag_reg="r--------" relation_reg="AuxP" head_reg="31" tp_n="1" line_n="7" lang="grc" hand_id="45" tm_word_id=""/>
    <word id="33" form_orig="μηνὶ" form_reg="μηνὶ" lemma_orig="μείς" postag_orig="n-s---md-" relation_orig="ATR" head_orig="32" lemma_reg="μείς" postag_reg="n-s---md-" relation_reg="ATR" head_reg="32" tp_n="1" line_n="7" lang="grc" hand_id="46" tm_word_id=""/>
    <word id="34" form_orig="Παχὼν" form_reg="Παχὼν" lemma_orig="Παχων" postag_orig="n-s---__-" relation_orig="ATR" head_orig="33" lemma_reg="Παχων" postag_reg="n-s---__-" relation_reg="ATR" head_reg="33" tp_n="1" line_n="7" lang="grc" hand_id="47" tm_word_id=""/>
    <word id="35" form_orig="❨τ(ο)ῦ❩" form_reg="τοῦ" lemma_orig="ὁ" postag_orig="l-s---__-" relation_orig="ATR" head_orig="38" lemma_reg="ὁ" postag_reg="l-s---ng-" relation_reg="ATR" head_reg="38" tp_n="1" line_n="7" lang="grc" hand_id="48" tm_word_id=""/>
    <word id="36" form_orig="αὐτ̣οῦ" form_reg="αὐτοῦ" lemma_orig="αὐτός" postag_orig="p-s---ng-" relation_orig="ATR" head_orig="38" lemma_reg="αὐτός" postag_reg="p-s---ng-" relation_reg="ATR" head_reg="38" tp_n="1" line_n="7" lang="grc" hand_id="49" tm_word_id=""/>
    <word id="37" form_orig="ιε|num:15|" form_reg="ιε|num:15|" lemma_orig="ιε" postag_orig="m-p---__-" relation_orig="ATR" head_orig="38" lemma_reg="ιε" postag_reg="m-p---__-" relation_reg="ATR" head_reg="38" tp_n="1" line_n="8" lang="grc" hand_id="50" tm_word_id=""/>
    <word id="38" form_orig="❨(ἔτους)❩" form_reg="ἔτους" lemma_orig="ἔτος" postag_orig="n-_---n_-" relation_orig="ATR" head_orig="33" lemma_reg="ἔτος" postag_reg="n-s---ng-" relation_reg="ATR" head_reg="33" tp_n="1" line_n="8" lang="grc" hand_id="51" tm_word_id=""/>
    <word id="39" form_orig="," form_reg="," lemma_orig="punc1" postag_orig="u--------" relation_orig="AuxX" head_orig="31" lemma_reg="punc1" postag_reg="u--------" relation_reg="AuxX" head_reg="31" tp_n="1" line_n="8" lang="grc" hand_id="52" tm_word_id=""/>
    <word id="40" form_orig="&lt;καὶ&gt;" form_reg="καὶ" lemma_orig="" postag_orig="" relation_orig="COORD" head_orig="0" lemma_reg="καί" postag_reg="c--------" relation_reg="COORD" head_reg="0" tp_n="1" line_n="8" lang="grc" hand_id="53" tm_word_id=""/>
    <word id="41" form_orig="ἀποτεισάτω" form_reg="ἀποτεισάτω" lemma_orig="ἀποτίνω" postag_orig="v3sama---" relation_orig="PRED_CO" head_orig="40" lemma_reg="ἀποτίνω" postag_reg="v3sama---" relation_reg="ATR_CO" head_reg="40" tp_n="1" line_n="8" lang="grc" hand_id="54" tm_word_id=""/>
    <word id="42" form_orig="∼ἑκαστω∽" form_reg="ἑκάστης" lemma_orig="ἕκαστος" postag_orig="a-s---md_" relation_orig="ATR" head_orig="43" lemma_reg="ἕκαστος" postag_reg="a-s---fg-" relation_reg="ATR" head_reg="43" tp_n="1" line_n="8" lang="grc" hand_id="55" tm_word_id=""/>
    <word id="43" form_orig="&lt;ἀρτάβης&gt;" form_reg="ἀρτάβης" lemma_orig="" postag_orig="" relation_orig="ATR" head_orig="50" lemma_reg="ἀρτάβη" postag_reg="n-s---fg-" relation_reg="ATR" head_reg="50" tp_n="1" line_n="8" lang="grc" hand_id="56" tm_word_id=""/>
    <word id="44" form_orig="πυροῦ" form_reg="πυροῦ" lemma_orig="πυρός" postag_orig="n-s---mg-" relation_orig="ATR" head_orig="43" lemma_reg="πυρός" postag_reg="n-s---mg-" relation_reg="ATR" head_reg="43" tp_n="1" line_n="8" lang="grc" hand_id="57" tm_word_id=""/>
    <word id="45" form_orig="ἧς" form_reg="ἧς" lemma_orig="ὅς" postag_orig="p-s---fg-" relation_orig="ATR" head_orig="48" lemma_reg="ὅς" postag_reg="p-s---fg-" relation_reg="ATR" head_reg="48" tp_n="1" line_n="8" lang="grc" hand_id="58" tm_word_id=""/>
    <word id="46" form_orig="ἐὰν" form_reg="ἐὰν" lemma_orig="ἐάν" postag_orig="c--------" relation_orig="AuxC" head_orig="41" lemma_reg="ἐάν" postag_reg="c--------" relation_reg="AuxC" head_reg="41" tp_n="1" line_n="8" lang="grc" hand_id="59" tm_word_id=""/>
    <word id="47" form_orig="μὴ" form_reg="μὴ" lemma_orig="μή" postag_orig="d-------_" relation_orig="AuxZ" head_orig="48" lemma_reg="μή" postag_reg="d-------_" relation_reg="AuxZ" head_reg="48" tp_n="1" line_n="8" lang="grc" hand_id="60" tm_word_id=""/>
    <word id="48" form_orig="ἀπ̣ο̣[δῶι]" form_reg="ἀποδῶι" lemma_orig="" postag_orig="" relation_orig="ADV" head_orig="46" lemma_reg="ἀποδίδωμι" postag_reg="v3sasa---" relation_reg="ADV" head_reg="46" tp_n="1" line_n="8" lang="grc" hand_id="61" tm_word_id=""/>
    <word id="49" form_orig="χ̣α̣λ̣κ̣οῦ" form_reg="χαλκοῦ" lemma_orig="χαλκός" postag_orig="n-s---mg-" relation_orig="ATR" head_orig="50" lemma_reg="χαλκός" postag_reg="n-s---mg-" relation_reg="ATR" head_reg="50" tp_n="1" line_n="9" lang="grc" hand_id="62" tm_word_id=""/>
    <word id="50" form_orig="δραχμὰς" form_reg="δραχμὰς" lemma_orig="δραχμή" postag_orig="n-p---fa-" relation_orig="OBJ_CO" head_orig="58" lemma_reg="δραχμή" postag_reg="n-p---fa-" relation_reg="OBJ_CO" head_reg="58" tp_n="1" line_n="9" lang="grc" hand_id="63" tm_word_id=""/>
    <word id="51" form_orig="δισχιλίας" form_reg="δισχιλίας" lemma_orig="δισχίλιοι" postag_orig="m-p---fa-" relation_orig="ATR" head_orig="50" lemma_reg="δισχίλιοι" postag_reg="m-p---fa-" relation_reg="ATR" head_reg="50" tp_n="1" line_n="9" lang="grc" hand_id="64" tm_word_id=""/>
    <word id="52" form_orig="τετρακοσίας|num:2400|" form_reg="τετρακοσίας|num:2400|" lemma_orig="τετρακόσιοι" postag_orig="m-p---fa-" relation_orig="ATR" head_orig="50" lemma_reg="τετρακόσιοι" postag_reg="m-p---fa-" relation_reg="ATR" head_reg="50" tp_n="1" line_n="9" lang="grc" hand_id="65" tm_word_id=""/>
    <word id="53" form_orig="," form_reg="," lemma_orig="punc1" postag_orig="u--------" relation_orig="AuxX" head_orig="58" lemma_reg="punc1" postag_reg="u--------" relation_reg="AuxX" head_reg="58" tp_n="1" line_n="9" lang="grc" hand_id="66" tm_word_id=""/>
    <word id="54" form_orig="κριθῆ[ς]" form_reg="κριθῆς" lemma_orig="κριθή" postag_orig="n-s---f_-" relation_orig="OBJ_CO" head_orig="66" lemma_reg="κριθή" postag_reg="n-s---fg-" relation_reg="ATR" head_reg="66" tp_n="1" line_n="9" lang="grc" hand_id="67" tm_word_id=""/>
    <word id="55" form_orig="χιλίας" form_reg="χιλίας" lemma_orig="χίλιοι" postag_orig="m-p---fa-" relation_orig="ATR" head_orig="65" lemma_reg="χίλιοι" postag_reg="m-p---fa-" relation_reg="ATR" head_reg="65" tp_n="1" line_n="10" lang="grc" hand_id="68" tm_word_id=""/>
    <word id="56" form_orig="τετρακοσίας|num:1400|" form_reg="τετρακοσίας|num:1400|" lemma_orig="τετρακόσιοι" postag_orig="m-p---fa-" relation_orig="ATR" head_orig="65" lemma_reg="τετρακόσιοι" postag_reg="m-p---fa-" relation_reg="ATR" head_reg="65" tp_n="1" line_n="10" lang="grc" hand_id="69" tm_word_id=""/>
    <word id="57" form_orig="," form_reg="," lemma_orig="punc1" postag_orig="u--------" relation_orig="AuxX" head_orig="58" lemma_reg="punc1" postag_reg="u--------" relation_reg="AuxX" head_reg="58" tp_n="1" line_n="10" lang="grc" hand_id="70" tm_word_id=""/>
    <word id="58" form_orig="καὶ" form_reg="καὶ" lemma_orig="καί" postag_orig="c--------" relation_orig="COORD" head_orig="41" lemma_reg="καί" postag_reg="c--------" relation_reg="COORD" head_reg="41" tp_n="1" line_n="10" lang="grc" hand_id="71" tm_word_id=""/>
    <word id="59" form_orig="❨(ἑβδόμην)❩" form_reg="ἑβδόμην" lemma_orig="ἕβδομος" postag_orig="a-_---___" relation_orig="ATR" head_orig="60" lemma_reg="ἕβδομος" postag_reg="a-s---fa-" relation_reg="ATR" head_reg="60" tp_n="1" line_n="10" lang="grc" hand_id="72" tm_word_id=""/>
    <word id="60" form_orig="μερίδα" form_reg="μερίδα" lemma_orig="μερίς" postag_orig="n-s---fa-" relation_orig="OBJ_CO" head_orig="58" lemma_reg="μερίς" postag_reg="n-s---fa-" relation_reg="OBJ_CO" head_reg="58" tp_n="1" line_n="10" lang="grc" hand_id="73" tm_word_id=""/>
    <word id="61" form_orig="τῶν" form_reg="τῶν" lemma_orig="ὁ" postag_orig="l-p---ng-" relation_orig="ATR" head_orig="62" lemma_reg="ὁ" postag_reg="l-p---ng-" relation_reg="ATR" head_reg="62" tp_n="1" line_n="10" lang="grc" hand_id="74" tm_word_id=""/>
    <word id="62" form_orig="γ̣[ε]∤νημάτων" form_reg="γε∤νημάτων" lemma_orig="γένημα" postag_orig="n-p---ng-" relation_orig="ATR" head_orig="60" lemma_reg="γένημα" postag_reg="n-p---ng-" relation_reg="ATR" head_reg="60" tp_n="1" line_n="10-11" lang="grc" hand_id="75" tm_word_id=""/>
    <word id="63" form_orig="πάντων" form_reg="πάντων" lemma_orig="πᾶς" postag_orig="a-p---ng-" relation_orig="ATR" head_orig="62" lemma_reg="πᾶς" postag_reg="a-p---ng-" relation_reg="ATR" head_reg="62" tp_n="1" line_n="11" lang="grc" hand_id="76" tm_word_id=""/>
    <word id="64" form_orig="·" form_reg="·" lemma_orig="punc1" postag_orig="u--------" relation_orig="AuxK" head_orig="0" lemma_reg="punc1" postag_reg="u--------" relation_reg="AuxK" head_reg="0" tp_n="1" line_n="11" lang="grc" hand_id="77" tm_word_id=""/>
    <word id="65" form_orig="δραχμας" form_reg="δραχμας" lemma_orig="" postag_orig="" relation_orig="OBJ_CO" head_orig="58" lemma_reg="" postag_reg="" relation_reg="OBJ_CO" head_reg="58" insertion_id="0053e" artificial="elliptic" tp_n="" line_n="None" lang="None" hand_id="78" tm_word_id=""/>
    <word id="66" form_orig="αρταβης" form_reg="αρταβης" lemma_orig="" postag_orig="" relation_orig="ATR" head_orig="65" lemma_reg="" postag_reg="" relation_reg="ATR" head_reg="65" insertion_id="0053f" artificial="elliptic" tp_n="" line_n="None" lang="None" hand_id="79" tm_word_id=""/>
    <word id="67" form_orig="ὄντι" form_reg="ὄντι" lemma_orig="" postag_orig="" relation_orig="ATR" head_orig="4" lemma_reg="" postag_reg="" relation_reg="ATR" head_reg="4" insertion_id="0008e" artificial="elliptic" tp_n="" line_n="None" lang="None" hand_id="80" tm_word_id=""/>
    <word id="68" form_orig="ᾧ" form_reg="ᾧ" lemma_orig="" postag_orig="" relation_orig="OBJ" head_orig="69" lemma_reg="" postag_reg="" relation_reg="OBJ" head_reg="69" insertion_id="0014e" artificial="elliptic" tp_n="" line_n="None" lang="None" hand_id="81" tm_word_id=""/>
    <word id="69" form_orig="ἐστὶ" form_reg="ἐστὶ" lemma_orig="" postag_orig="" relation_orig="ATR" head_orig="4" lemma_reg="" postag_reg="" relation_reg="ATR" head_reg="4" insertion_id="0014f" artificial="elliptic" tp_n="" line_n="None" lang="None" hand_id="82" tm_word_id=""/>
    <word id="70" form_orig="καὶ" form_reg="καὶ" lemma_orig="" postag_orig="" relation_orig="COORD" head_orig="18" lemma_reg="" postag_reg="" relation_reg="COORD" head_reg="18" insertion_id="0020e" artificial="elliptic" tp_n="" line_n="None" lang="None" hand_id="83" tm_word_id=""/>
    <word id="71" form_orig="καὶ" form_reg="καὶ" lemma_orig="" postag_orig="" relation_orig="COORD" head_orig="22" lemma_reg="" postag_reg="" relation_reg="COORD" head_reg="22" insertion_id="0023e" artificial="elliptic" tp_n="" line_n="None" lang="None" hand_id="84" tm_word_id=""/>
  </sentence>
  <sentence id="3">
    <word id="1" form_orig="τὸ" form_reg="τὸ" lemma_orig="ὁ" postag_orig="l-s---na-" relation_orig="ATR" head_orig="3" lemma_reg="ὁ" postag_reg="l-s---na-" relation_reg="ATR" head_reg="3" tp_n="1" line_n="11" lang="grc" hand_id="85" tm_word_id=""/>
    <word id="2" form_orig="δὲ" form_reg="δὲ" lemma_orig="δέ" postag_orig="c--------" relation_orig="COORD" head_orig="0" lemma_reg="δέ" postag_reg="c--------" relation_reg="COORD" head_reg="0" tp_n="1" line_n="11" lang="grc" hand_id="86" tm_word_id=""/>
    <word id="3" form_orig="δάνειον" form_reg="δάνειον" lemma_orig="δάνειον" postag_orig="n-s---na-" relation_orig="OBJ" head_orig="5" lemma_reg="δάνειον" postag_reg="n-s---na-" relation_reg="OBJ" head_reg="5" tp_n="1" line_n="11" lang="grc" hand_id="87" tm_word_id=""/>
    <word id="4" form_orig="τοῦτο" form_reg="τοῦτο" lemma_orig="οὗτος" postag_orig="p-s---na-" relation_orig="ATR" head_orig="3" lemma_reg="οὗτος" postag_reg="p-s---na-" relation_reg="ATR" head_reg="3" tp_n="1" line_n="11" lang="grc" hand_id="88" tm_word_id=""/>
    <word id="5" form_orig="ἀποδότω" form_reg="ἀποδότω" lemma_orig="ἀποδίδωμι" postag_orig="v3sama---" relation_orig="PRED_CO" head_orig="2" lemma_reg="ἀποδίδωμι" postag_reg="v3sama---" relation_reg="PRED_CO" head_reg="2" tp_n="1" line_n="12" lang="grc" hand_id="89" tm_word_id=""/>
    <word id="6" form_orig="∼οἱ∽" form_reg="ὁ" lemma_orig="ὁ" postag_orig="l-p---mn-" relation_orig="ATR" head_orig="7" lemma_reg="ὁ" postag_reg="l-s---mn-" relation_reg="ATR" head_reg="7" tp_n="1" line_n="12" lang="grc" hand_id="90" tm_word_id=""/>
    <word id="7" form_orig="δεδανεισμένος" form_reg="δεδανεισμένος" lemma_orig="δανείζω" postag_orig="v-srpemn-" relation_orig="SBJ" head_orig="5" lemma_reg="δανείζω" postag_reg="v-srpemn-" relation_reg="SBJ" head_reg="5" tp_n="1" line_n="12" lang="grc" hand_id="91" tm_word_id=""/>
    <word id="8" form_orig="Ὥρωι" form_reg="Ὥρωι" lemma_orig="Ὡρος" postag_orig="n-s---md-" relation_orig="OBJ" head_orig="5" lemma_reg="Ὡρος" postag_reg="n-s---md-" relation_reg="OBJ" head_reg="5" tp_n="1" line_n="12" lang="grc" hand_id="92" tm_word_id=""/>
    <word id="9" form_orig="ἐ̣ν" form_reg="ἐν" lemma_orig="ἐν" postag_orig="r--------" relation_orig="AuxP" head_orig="5" lemma_reg="ἐν" postag_reg="r--------" relation_reg="AuxP" head_reg="5" tp_n="1" line_n="12" lang="grc" hand_id="93" tm_word_id=""/>
    <word id="10" form_orig="μηνὶ" form_reg="μηνὶ" lemma_orig="μείς" postag_orig="n-s---md-" relation_orig="ADV" head_orig="9" lemma_reg="μείς" postag_reg="n-s---md-" relation_reg="ADV" head_reg="9" tp_n="1" line_n="12" lang="grc" hand_id="94" tm_word_id=""/>
    <word id="11" form_orig="Παχὼν" form_reg="Παχὼν" lemma_orig="Παχων" postag_orig="n-s---__-" relation_orig="ATR" head_orig="10" lemma_reg="Παχων" postag_reg="n-s---__-" relation_reg="ATR" head_reg="10" tp_n="1" line_n="13" lang="grc" hand_id="95" tm_word_id=""/>
    <word id="12" form_orig="τοῦ" form_reg="τοῦ" lemma_orig="ὁ" postag_orig="l-s---ng-" relation_orig="ATR" head_orig="14" lemma_reg="ὁ" postag_reg="l-s---ng-" relation_reg="ATR" head_reg="14" tp_n="1" line_n="13" lang="grc" hand_id="96" tm_word_id=""/>
    <word id="13" form_orig="αὐτοῦ" form_reg="αὐτοῦ" lemma_orig="αὐτός" postag_orig="p-s---ng-" relation_orig="ATR" head_orig="14" lemma_reg="αὐτός" postag_reg="p-s---ng-" relation_reg="ATR" head_reg="14" tp_n="1" line_n="13" lang="grc" hand_id="97" tm_word_id=""/>
    <word id="14" form_orig="❨(ἔτους)❩" form_reg="ἔτους" lemma_orig="ἔτος" postag_orig="n-_---n_-" relation_orig="ATR" head_orig="10" lemma_reg="ἔτος" postag_reg="n-s---ng-" relation_reg="ATR" head_reg="10" tp_n="1" line_n="13" lang="grc" hand_id="98" tm_word_id=""/>
    <word id="15" form_orig="&lt;καθαρὸν&gt;" form_reg="καθαρὸν" lemma_orig="" postag_orig="" relation_orig="OCOMP_CO" head_orig="18" lemma_reg="καθαρός" postag_reg="a-s---na-" relation_reg="OCOMP_CO" head_reg="18" tp_n="1" line_n="13" lang="grc" hand_id="99" tm_word_id=""/>
    <word id="16" form_orig="ἀπὸ" form_reg="ἀπὸ" lemma_orig="ἀπό" postag_orig="r--------" relation_orig="AuxP" head_orig="15" lemma_reg="ἀπό" postag_reg="r--------" relation_reg="AuxP" head_reg="15" tp_n="1" line_n="13" lang="grc" hand_id="100" tm_word_id=""/>
    <word id="17" form_orig="παντὸς" form_reg="παντὸς" lemma_orig="πᾶς" postag_orig="a-s---mg-" relation_orig="ATR" head_orig="16" lemma_reg="πᾶς" postag_reg="a-s---mg-" relation_reg="ATR" head_reg="16" tp_n="1" line_n="13" lang="grc" hand_id="101" tm_word_id=""/>
    <word id="18" form_orig="κα̣[ὶ]" form_reg="καὶ" lemma_orig="καί" postag_orig="c--------" relation_orig="COORD" head_orig="5" lemma_reg="καί" postag_reg="c--------" relation_reg="COORD" head_reg="5" tp_n="1" line_n="13" lang="grc" hand_id="102" tm_word_id=""/>
    <word id="19" form_orig="ἀποκαθεσταμένον" form_reg="ἀποκαθεσταμένον" lemma_orig="ἀποκαθίστημι" postag_orig="v-srpena-" relation_orig="OCOMP_CO" head_orig="18" lemma_reg="ἀποκαθίστημι" postag_reg="v-srpena-" relation_reg="OCOMP_CO" head_reg="18" tp_n="1" line_n="14" lang="grc" hand_id="103" tm_word_id=""/>
    <word id="20" form_orig="εἰς" form_reg="εἰς" lemma_orig="εἰς" postag_orig="r--------" relation_orig="AuxP" head_orig="19" lemma_reg="εἰς" postag_reg="r--------" relation_reg="AuxP" head_reg="19" tp_n="1" line_n="14" lang="grc" hand_id="104" tm_word_id=""/>
    <word id="21" form_orig="οἶκον" form_reg="οἶκον" lemma_orig="οἶκος" postag_orig="n-s---ma-" relation_orig="OBJ" head_orig="20" lemma_reg="οἶκος" postag_reg="n-s---ma-" relation_reg="OBJ" head_reg="20" tp_n="1" line_n="14" lang="grc" hand_id="105" tm_word_id=""/>
    <word id="22" form_orig="&lt;ἐν&gt;" form_reg="ἐν" lemma_orig="" postag_orig="" relation_orig="" head_orig="" lemma_reg="ἐν" postag_reg="r--------" relation_reg="AuxP" head_reg="5" tp_n="1" line_n="14" lang="grc" hand_id="106" tm_word_id=""/>
    <word id="23" form_orig="τοῖς" form_reg="τοῖς" lemma_orig="ὁ" postag_orig="l-p---nd-" relation_orig="ATR" head_orig="24" lemma_reg="ὁ" postag_reg="l-p---nd-" relation_reg="ATR" head_reg="24" tp_n="1" line_n="14" lang="grc" hand_id="107" tm_word_id=""/>
    <word id="24" form_orig="πεδίοι̣[ς]" form_reg="πεδίοις" lemma_orig="πεδίον" postag_orig="n-p---nd-" relation_orig="ADV" head_orig="5" lemma_reg="πεδίον" postag_reg="n-p---nd-" relation_reg="ADV" head_reg="22" tp_n="1" line_n="14" lang="grc" hand_id="108" tm_word_id=""/>
    <word id="25" form_orig="&lt;ἰδίοις&gt;" form_reg="ἰδίοις" lemma_orig="" postag_orig="" relation_orig="" head_orig="" lemma_reg="ἴδιος" postag_reg="a-p---nd-" relation_reg="ATR" head_reg="26" tp_n="1" line_n="14" lang="grc" hand_id="109" tm_word_id=""/>
    <word id="26" form_orig="ἀνηλώμασι" form_reg="ἀνηλώμασι" lemma_orig="ἀνήλωμα" postag_orig="n-p---nd-" relation_orig="ADV" head_orig="5" lemma_reg="ἀνήλωμα" postag_reg="n-p---nd-" relation_reg="ADV" head_reg="5" tp_n="1" line_n="15" lang="grc" hand_id="110" tm_word_id=""/>
    <word id="27" form_orig="μέτρῳ" form_reg="μέτρῳ" lemma_orig="μέτρον" postag_orig="n-s---nd-" relation_orig="ADV" head_orig="5" lemma_reg="μέτρον" postag_reg="n-s---nd-" relation_reg="ADV" head_reg="5" tp_n="1" line_n="15" lang="grc" hand_id="111" tm_word_id=""/>
    <word id="28" form_orig="ᾧ" form_reg="ᾧ" lemma_orig="ὅς" postag_orig="p-s---nd-" relation_orig="ADV" head_orig="30" lemma_reg="ὅς" postag_reg="p-s---nd-" relation_reg="ADV" head_reg="30" tp_n="1" line_n="15" lang="grc" hand_id="112" tm_word_id=""/>
    <word id="29" form_orig="καὶ" form_reg="καὶ" lemma_orig="καί" postag_orig="d-------_" relation_orig="AuxZ" head_orig="30" lemma_reg="καί" postag_reg="d-------_" relation_reg="AuxZ" head_reg="30" tp_n="1" line_n="15" lang="grc" hand_id="113" tm_word_id=""/>
    <word id="30" form_orig="παρείληφε̣ν̣" form_reg="παρείληφεν" lemma_orig="παραλαμβάνω" postag_orig="v3sria---" relation_orig="ATR" head_orig="27" lemma_reg="παραλαμβάνω" postag_reg="v3sria---" relation_reg="ATR" head_reg="27" tp_n="1" line_n="15" lang="grc" hand_id="114" tm_word_id=""/>
    <word id="31" form_orig="·" form_reg="·" lemma_orig="punc1" postag_orig="u--------" relation_orig="AuxK" head_orig="0" lemma_reg="punc1" postag_reg="u--------" relation_reg="AuxK" head_reg="0" tp_n="1" line_n="15" lang="grc" hand_id="115" tm_word_id=""/>
  </sentence>
  <sentence id="4">
    <word id="1" form_orig="ἐὰν" form_reg="ἐὰν" lemma_orig="ἐάν" postag_orig="c--------" relation_orig="AuxC" head_orig="14" lemma_reg="ἐάν" postag_reg="c--------" relation_reg="AuxC" head_reg="14" tp_n="1" line_n="16" lang="grc" hand_id="116" tm_word_id=""/>
    <word id="2" form_orig="δὲ" form_reg="δὲ" lemma_orig="δέ" postag_orig="c--------" relation_orig="COORD" head_orig="0" lemma_reg="δέ" postag_reg="c--------" relation_reg="COORD" head_reg="0" tp_n="1" line_n="16" lang="grc" hand_id="117" tm_word_id=""/>
    <word id="3" form_orig="μὴ" form_reg="μὴ" lemma_orig="μή" postag_orig="d-------_" relation_orig="AuxZ" head_orig="4" lemma_reg="μή" postag_reg="d-------_" relation_reg="AuxZ" head_reg="4" tp_n="1" line_n="16" lang="grc" hand_id="118" tm_word_id=""/>
    <word id="4" form_orig="∼ἀποδωσιν∽" form_reg="ἀποδῷ" lemma_orig="ἀποδίδωμι" postag_orig="v3pasa---" relation_orig="ADV_CO" head_orig="9" lemma_reg="ἀποδίδωμι" postag_reg="v3sasa---" relation_reg="ADV_CO" head_reg="9" tp_n="1" line_n="16" lang="grc" hand_id="119" tm_word_id=""/>
    <word id="5" form_orig="ἐ̣ν" form_reg="ἐν" lemma_orig="ἐν" postag_orig="r--------" relation_orig="AuxP" head_orig="4" lemma_reg="ἐν" postag_reg="r--------" relation_reg="AuxP" head_reg="4" tp_n="1" line_n="16" lang="grc" hand_id="120" tm_word_id=""/>
    <word id="6" form_orig="τῷ" form_reg="τῷ" lemma_orig="ὁ" postag_orig="l-s---md-" relation_orig="ATR" head_orig="8" lemma_reg="ὁ" postag_reg="l-s---md-" relation_reg="ATR" head_reg="8" tp_n="1" line_n="16" lang="grc" hand_id="121" tm_word_id=""/>
    <word id="7" form_orig="ὡρισμένῳ" form_reg="ὡρισμένῳ" lemma_orig="ὁρίζω" postag_orig="v-srpemd-" relation_orig="ATR" head_orig="8" lemma_reg="ὁρίζω" postag_reg="v-srpemd-" relation_reg="ATR" head_reg="8" tp_n="1" line_n="16" lang="grc" hand_id="122" tm_word_id=""/>
    <word id="8" form_orig="χρόνωι" form_reg="χρόνωι" lemma_orig="χρόνος" postag_orig="n-s---md-" relation_orig="ADV" head_orig="5" lemma_reg="χρόνος" postag_reg="n-s---md-" relation_reg="ADV" head_reg="5" tp_n="1" line_n="17" lang="grc" hand_id="123" tm_word_id=""/>
    <word id="9" form_orig="ἢ" form_reg="ἢ" lemma_orig="ἤ1" postag_orig="c--------" relation_orig="COORD" head_orig="1" lemma_reg="ἤ1" postag_reg="c--------" relation_reg="COORD" head_reg="1" tp_n="1" line_n="17" lang="grc" hand_id="124" tm_word_id=""/>
    <word id="10" form_orig="μὴ" form_reg="μὴ" lemma_orig="μή" postag_orig="d-------_" relation_orig="AuxZ" head_orig="11" lemma_reg="μή" postag_reg="d-------_" relation_reg="AuxZ" head_reg="11" tp_n="1" line_n="17" lang="grc" hand_id="125" tm_word_id=""/>
    <word id="11" form_orig="∼ποιωσιν∽" form_reg="ποιῇ" lemma_orig="ποιέω" postag_orig="v3ppsa---" relation_orig="ADV_CO" head_orig="9" lemma_reg="ποιέω" postag_reg="v3spsa---" relation_reg="ADV_CO" head_reg="9" tp_n="1" line_n="17" lang="grc" hand_id="126" tm_word_id=""/>
    <word id="12" form_orig="καθὰ" form_reg="καθὰ" lemma_orig="καθά" postag_orig="d--------" relation_orig="ADV" head_orig="13" lemma_reg="καθά" postag_reg="d--------" relation_reg="ADV" head_reg="13" tp_n="1" line_n="17" lang="grc" hand_id="127" tm_word_id=""/>
    <word id="13" form_orig="γέγραπται" form_reg="γέγραπται" lemma_orig="γράφω" postag_orig="v3srie---" relation_orig="ADV" head_orig="11" lemma_reg="γράφω" postag_reg="v3srie---" relation_reg="ADV" head_reg="11" tp_n="1" line_n="17" lang="grc" hand_id="128" tm_word_id=""/>
    <word id="14" form_orig="ἀπ̣[ο]∤τεισάτω" form_reg="ἀπο∤τεισάτω" lemma_orig="ἀποτίνω" postag_orig="v3sama---" relation_orig="PRED_CO" head_orig="29" lemma_reg="ἀποτίνω" postag_reg="v3sama---" relation_reg="PRED_CO" head_reg="29" tp_n="1" line_n="17-18" lang="grc" hand_id="129" tm_word_id=""/>
    <word id="15" form_orig="ἐν" form_reg="ἐν" lemma_orig="ἐν" postag_orig="r--------" relation_orig="AuxP" head_orig="14" lemma_reg="ἐν" postag_reg="r--------" relation_reg="AuxP" head_reg="14" tp_n="1" line_n="18" lang="grc" hand_id="130" tm_word_id=""/>
    <word id="16" form_orig="τῷ" form_reg="τῷ" lemma_orig="ὁ" postag_orig="l-s---md-" relation_orig="ATR" head_orig="18" lemma_reg="ὁ" postag_reg="l-s---md-" relation_reg="ATR" head_reg="18" tp_n="1" line_n="18" lang="grc" hand_id="131" tm_word_id=""/>
    <word id="17" form_orig="ἐχομένωι" form_reg="ἐχομένωι" lemma_orig="ἔχω" postag_orig="v-sppemd-" relation_orig="ATR" head_orig="18" lemma_reg="ἔχω" postag_reg="v-sppemd-" relation_reg="ATR" head_reg="18" tp_n="1" line_n="18" lang="grc" hand_id="132" tm_word_id=""/>
    <word id="18" form_orig="μηνὶ" form_reg="μηνὶ" lemma_orig="μείς" postag_orig="n-s---md-" relation_orig="ADV" head_orig="15" lemma_reg="μείς" postag_reg="n-s---md-" relation_reg="ADV" head_reg="15" tp_n="1" line_n="18" lang="grc" hand_id="133" tm_word_id=""/>
    <word id="19" form_orig="παραχρ̣ῆ̣[μα]" form_reg="παραχρῆμα" lemma_orig="παραχρῆμα" postag_orig="d--------" relation_orig="ADV" head_orig="14" lemma_reg="παραχρῆμα" postag_reg="d--------" relation_reg="ADV" head_reg="14" tp_n="1" line_n="18" lang="grc" hand_id="134" tm_word_id=""/>
    <word id="20" form_orig="ἡμιόλιον" form_reg="ἡμιόλιον" lemma_orig="ἡμιόλιος" postag_orig="a-s---na-" relation_orig="OBJ_CO" head_orig="21" lemma_reg="ἡμιόλιος" postag_reg="a-s---na-" relation_reg="OBJ_CO" head_reg="21" tp_n="1" line_n="19" lang="grc" hand_id="135" tm_word_id=""/>
    <word id="21" form_orig="ἢ" form_reg="ἢ" lemma_orig="ἤ1" postag_orig="c--------" relation_orig="COORD" head_orig="14" lemma_reg="ἤ1" postag_reg="c--------" relation_reg="COORD" head_reg="14" tp_n="1" line_n="19" lang="grc" hand_id="136" tm_word_id=""/>
    <word id="22" form_orig="τὴν" form_reg="τὴν" lemma_orig="ὁ" postag_orig="l-s---fa-" relation_orig="ATR" head_orig="27" lemma_reg="ὁ" postag_reg="l-s---fa-" relation_reg="ATR" head_reg="27" tp_n="1" line_n="19" lang="grc" hand_id="137" tm_word_id=""/>
    <word id="23" form_orig="ἐσομένην" form_reg="ἐσομένην" lemma_orig="εἰμί" postag_orig="v-sfpmfa-" relation_orig="ATR" head_orig="27" lemma_reg="εἰμί" postag_reg="v-sfpmfa-" relation_reg="ATR" head_reg="27" tp_n="1" line_n="19" lang="grc" hand_id="138" tm_word_id=""/>
    <word id="24" form_orig="ἐν" form_reg="ἐν" lemma_orig="ἐν" postag_orig="r--------" relation_orig="AuxP" head_orig="27" lemma_reg="ἐν" postag_reg="r--------" relation_reg="AuxP" head_reg="27" tp_n="1" line_n="19" lang="grc" hand_id="139" tm_word_id=""/>
    <word id="25" form_orig="τῇ" form_reg="τῇ" lemma_orig="ὁ" postag_orig="l-s---fd-" relation_orig="ATR" head_orig="26" lemma_reg="ὁ" postag_reg="l-s---fd-" relation_reg="ATR" head_reg="26" tp_n="1" line_n="19" lang="grc" hand_id="140" tm_word_id=""/>
    <word id="26" form_orig="ἀγορᾶι" form_reg="ἀγορᾶι" lemma_orig="ἀγορά" postag_orig="n-s---fd-" relation_orig="ATR" head_orig="24" lemma_reg="ἀγορά" postag_reg="n-s---fd-" relation_reg="ATR" head_reg="24" tp_n="1" line_n="19" lang="grc" hand_id="141" tm_word_id=""/>
    <word id="27" form_orig="∼τειμήν∽" form_reg="τιμήν" lemma_orig="τιμή" postag_orig="n-s---fa-" relation_orig="OBJ_CO" head_orig="21" lemma_reg="τιμή" postag_reg="n-s---fa-" relation_reg="OBJ_CO" head_reg="21" tp_n="1" line_n="20" lang="grc" hand_id="142" tm_word_id=""/>
    <word id="28" form_orig="," form_reg="," lemma_orig="punc1" postag_orig="u--------" relation_orig="AuxX" head_orig="29" lemma_reg="punc1" postag_reg="u--------" relation_reg="AuxX" head_reg="29" tp_n="1" line_n="20" lang="grc" hand_id="143" tm_word_id=""/>
    <word id="29" form_orig="καὶ" form_reg="καὶ" lemma_orig="καί" postag_orig="c--------" relation_orig="COORD" head_orig="2" lemma_reg="καί" postag_reg="c--------" relation_reg="COORD" head_reg="2" tp_n="1" line_n="20" lang="grc" hand_id="144" tm_word_id=""/>
    <word id="30" form_orig="ἡ" form_reg="ἡ" lemma_orig="ὁ" postag_orig="l-s---fn-" relation_orig="ATR" head_orig="31" lemma_reg="ὁ" postag_reg="l-s---fn-" relation_reg="ATR" head_reg="31" tp_n="1" line_n="20" lang="grc" hand_id="145" tm_word_id=""/>
    <word id="31" form_orig="πρᾶξις" form_reg="πρᾶξις" lemma_orig="πρᾶξις" postag_orig="n-s---fn-" relation_orig="SBJ" head_orig="32" lemma_reg="πρᾶξις" postag_reg="n-s---fn-" relation_reg="SBJ" head_reg="32" tp_n="1" line_n="20" lang="grc" hand_id="146" tm_word_id=""/>
    <word id="32" form_orig="ἔστω" form_reg="ἔστω" lemma_orig="εἰμί" postag_orig="v3spma---" relation_orig="PRED_CO" head_orig="29" lemma_reg="εἰμί" postag_reg="v3spma---" relation_reg="PRED_CO" head_reg="29" tp_n="1" line_n="20" lang="grc" hand_id="147" tm_word_id=""/>
    <word id="33" form_orig="Ὥρῳ" form_reg="Ὥρῳ" lemma_orig="Ὡρος" postag_orig="n-s---md-" relation_orig="OBJ" head_orig="32" lemma_reg="Ὡρος" postag_reg="n-s---md-" relation_reg="OBJ" head_reg="32" tp_n="1" line_n="20" lang="grc" hand_id="148" tm_word_id=""/>
    <word id="34" form_orig="ἐκ" form_reg="ἐκ" lemma_orig="ἐκ" postag_orig="r--------" relation_orig="AuxP" head_orig="48" lemma_reg="ἐκ" postag_reg="r--------" relation_reg="AuxP" head_reg="48" tp_n="1" line_n="20" lang="grc" hand_id="149" tm_word_id=""/>
    <word id="35" form_orig="τοῦ" form_reg="τοῦ" lemma_orig="ὁ" postag_orig="l-s---mg-" relation_orig="ATR" head_orig="36" lemma_reg="ὁ" postag_reg="l-s---mg-" relation_reg="ATR" head_reg="36" tp_n="1" line_n="20" lang="grc" hand_id="150" tm_word_id=""/>
    <word id="36" form_orig="δεδανεισμένου" form_reg="δεδανεισμένου" lemma_orig="δανείζω" postag_orig="v-srpemg-" relation_orig="ADV_CO" head_orig="34" lemma_reg="δανείζω" postag_reg="v-srpemg-" relation_reg="ADV_CO" head_reg="34" tp_n="1" line_n="21" lang="grc" hand_id="151" tm_word_id=""/>
    <word id="37" form_orig="καὶ" form_reg="καὶ" lemma_orig="καί" postag_orig="c--------" relation_orig="AuxY" head_orig="48" lemma_reg="καί" postag_reg="c--------" relation_reg="AuxY" head_reg="48" tp_n="1" line_n="21" lang="grc" hand_id="152" tm_word_id=""/>
    <word id="38" form_orig="ἐξ" form_reg="ἐξ" lemma_orig="ἐκ" postag_orig="r--------" relation_orig="AuxP" head_orig="48" lemma_reg="ἐκ" postag_reg="r--------" relation_reg="AuxP" head_reg="48" tp_n="1" line_n="21" lang="grc" hand_id="153" tm_word_id=""/>
    <word id="39" form_orig="ἑνὸς|num:1|" form_reg="ἑνὸς|num:1|" lemma_orig="εἷς" postag_orig="m-s---mg-" relation_orig="ADV_CO" head_orig="40" lemma_reg="εἷς" postag_reg="m-s---mg-" relation_reg="ADV_CO" head_reg="40" tp_n="1" line_n="21" lang="grc" hand_id="154" tm_word_id=""/>
    <word id="40" form_orig="καὶ" form_reg="καὶ" lemma_orig="καί" postag_orig="c--------" relation_orig="COORD" head_orig="38" lemma_reg="καί" postag_reg="c--------" relation_reg="COORD" head_reg="38" tp_n="1" line_n="21" lang="grc" hand_id="155" tm_word_id=""/>
    <word id="41" form_orig="ἑκάστο̣υ" form_reg="ἑκάστου" lemma_orig="ἕκαστος" postag_orig="a-s---mg-" relation_orig="ADV_CO" head_orig="40" lemma_reg="ἕκαστος" postag_reg="a-s---mg-" relation_reg="ADV_CO" head_reg="40" tp_n="1" line_n="21" lang="grc" hand_id="156" tm_word_id=""/>
    <word id="42" form_orig="αὐτῶ̣ν" form_reg="αὐτῶν" lemma_orig="αὐτός" postag_orig="p-p---mg-" relation_orig="ATR" head_orig="40" lemma_reg="αὐτός" postag_reg="p-p---mg-" relation_reg="ATR" head_reg="40" tp_n="1" line_n="22" lang="grc" hand_id="157" tm_word_id=""/>
    <word id="43" form_orig="καὶ" form_reg="καὶ" lemma_orig="καί" postag_orig="c--------" relation_orig="AuxY" head_orig="48" lemma_reg="καί" postag_reg="c--------" relation_reg="AuxY" head_reg="48" tp_n="1" line_n="22" lang="grc" hand_id="158" tm_word_id=""/>
    <word id="44" form_orig="ἐξ" form_reg="ἐξ" lemma_orig="ἐκ" postag_orig="r--------" relation_orig="AuxP" head_orig="48" lemma_reg="ἐκ" postag_reg="r--------" relation_reg="AuxP" head_reg="48" tp_n="1" line_n="22" lang="grc" hand_id="159" tm_word_id=""/>
    <word id="45" form_orig="οὗ" form_reg="οὗ" lemma_orig="ὅς" postag_orig="p-s---mg-" relation_orig="OBJ" head_orig="47" lemma_reg="ὅς" postag_reg="p-s---mg-" relation_reg="OBJ" head_reg="47" tp_n="1" line_n="22" lang="grc" hand_id="160" tm_word_id=""/>
    <word id="46" form_orig="ἂν" form_reg="ἂν" lemma_orig="ἄν1" postag_orig="d--------" relation_orig="AuxY" head_orig="47" lemma_reg="ἄν1" postag_reg="d--------" relation_reg="AuxY" head_reg="47" tp_n="1" line_n="22" lang="grc" hand_id="161" tm_word_id=""/>
    <word id="47" form_orig="∼αἱηραται∽" form_reg="αἵρηται" lemma_orig="αἱρέω" postag_orig="v3spse---" relation_orig="ADV_CO" head_orig="44" lemma_reg="αἱρέω" postag_reg="v3spse---" relation_reg="ADV_CO" head_reg="44" tp_n="1" line_n="22" lang="grc" hand_id="162" tm_word_id=""/>
    <word id="48" form_orig="καὶ" form_reg="καὶ" lemma_orig="καί" postag_orig="c--------" relation_orig="COORD" head_orig="32" lemma_reg="καί" postag_reg="c--------" relation_reg="COORD" head_reg="32" tp_n="1" line_n="22" lang="grc" hand_id="163" tm_word_id=""/>
    <word id="49" form_orig="ἐκ" form_reg="ἐκ" lemma_orig="ἐκ" postag_orig="r--------" relation_orig="AuxP" head_orig="48" lemma_reg="ἐκ" postag_reg="r--------" relation_reg="AuxP" head_reg="48" tp_n="1" line_n="22" lang="grc" hand_id="164" tm_word_id=""/>
    <word id="50" form_orig="τῶν" form_reg="τῶν" lemma_orig="ὁ" postag_orig="l-p---ng-" relation_orig="ATR" head_orig="51" lemma_reg="ὁ" postag_reg="l-p---ng-" relation_reg="ATR" head_reg="51" tp_n="1" line_n="22" lang="grc" hand_id="165" tm_word_id=""/>
    <word id="51" form_orig="ὑπαρχόντων" form_reg="ὑπαρχόντων" lemma_orig="ὑπάρχω" postag_orig="v-pppang-" relation_orig="ADV_CO" head_orig="49" lemma_reg="ὑπάρχω" postag_reg="v-pppang-" relation_reg="ADV_CO" head_reg="49" tp_n="1" line_n="23" lang="grc" hand_id="166" tm_word_id=""/>
    <word id="52" form_orig="αὐτῷ" form_reg="αὐτῷ" lemma_orig="αὐτός" postag_orig="p-s---md-" relation_orig="ATR" head_orig="51" lemma_reg="αὐτός" postag_reg="p-s---md-" relation_reg="ATR" head_reg="51" tp_n="1" line_n="23" lang="grc" hand_id="167" tm_word_id=""/>
    <word id="53" form_orig="πάντων" form_reg="πάντων" lemma_orig="πᾶς" postag_orig="a-p---ng-" relation_orig="ATR" head_orig="51" lemma_reg="πᾶς" postag_reg="a-p---ng-" relation_reg="ATR" head_reg="51" tp_n="1" line_n="23" lang="grc" hand_id="168" tm_word_id=""/>
    <word id="54" form_orig="πράσσοντι" form_reg="πράσσοντι" lemma_orig="πράσσω" postag_orig="v-sppamd-" relation_orig="APOS" head_orig="33" lemma_reg="πράσσω" postag_reg="v-sppamd-" relation_reg="APOS" head_reg="33" tp_n="1" line_n="23" lang="grc" hand_id="169" tm_word_id=""/>
    <word id="55" form_orig="καθάπερ" form_reg="καθάπερ" lemma_orig="καθά" postag_orig="c--------" relation_orig="AuxC" head_orig="54" lemma_reg="καθά" postag_reg="c--------" relation_reg="AuxC" head_reg="54" tp_n="1" line_n="24" lang="grc" hand_id="170" tm_word_id=""/>
    <word id="56" form_orig="ἐκ" form_reg="ἐκ" lemma_orig="ἐκ" postag_orig="r--------" relation_orig="AuxP" head_orig="59" lemma_reg="ἐκ" postag_reg="r--------" relation_reg="AuxP" head_reg="59" tp_n="1" line_n="24" lang="grc" hand_id="171" tm_word_id=""/>
    <word id="57" form_orig="δίκης" form_reg="δίκης" lemma_orig="δίκη" postag_orig="n-s---fg-" relation_orig="ATR" head_orig="56" lemma_reg="δίκη" postag_reg="n-s---fg-" relation_reg="ATR" head_reg="56" tp_n="1" line_n="24" lang="grc" hand_id="172" tm_word_id=""/>
    <word id="58" form_orig="." form_reg="." lemma_orig="punc1" postag_orig="u--------" relation_orig="AuxK" head_orig="0" lemma_reg="punc1" postag_reg="u--------" relation_reg="AuxK" head_reg="0" tp_n="1" line_n="24" lang="grc" hand_id="173" tm_word_id=""/>
  </sentence>
  <sentence id="5">
    <word id="1" form_orig="Ἑρμίας" form_reg="Ἑρμίας" lemma_orig="Ἑρμίας" postag_orig="n-s---mn-" relation_orig="SBJ" head_orig="5" lemma_reg="Ἑρμίας" postag_reg="n-s---mn-" relation_reg="SBJ" head_reg="5" tp_n="1" line_n="25" lang="grc" hand_id="174" tm_word_id=""/>
    <word id="2" form_orig="ὁ" form_reg="ὁ" lemma_orig="ὁ" postag_orig="p-s---mn-" relation_orig="ATR" head_orig="1" lemma_reg="ὁ" postag_reg="p-s---mn-" relation_reg="ATR" head_reg="1" tp_n="1" line_n="25" lang="grc" hand_id="175" tm_word_id=""/>
    <word id="3" form_orig="παρὰ" form_reg="παρὰ" lemma_orig="παρά" postag_orig="r--------" relation_orig="AuxP" head_orig="2" lemma_reg="παρά" postag_reg="r--------" relation_reg="AuxP" head_reg="2" tp_n="1" line_n="25" lang="grc" hand_id="176" tm_word_id=""/>
    <word id="4" form_orig="Πανίσκου" form_reg="Πανίσκου" lemma_orig="Πανίσκος" postag_orig="n-s---mg-" relation_orig="ATR" head_orig="3" lemma_reg="Πανίσκος" postag_reg="n-s---mg-" relation_reg="ATR" head_reg="3" tp_n="1" line_n="25" lang="grc" hand_id="177" tm_word_id=""/>
    <word id="5" form_orig="❨κεχρη(μάτικα)❩" form_reg="κεχρημάτικα" lemma_orig="χρηματίζω" postag_orig="v__r__---" relation_orig="PRED" head_orig="0" lemma_reg="χρηματίζω" postag_reg="v1sria---" relation_reg="PRED" head_reg="0" tp_n="1" line_n="25" lang="grc" hand_id="178" tm_word_id=""/>
    <word id="6" form_orig="." form_reg="." lemma_orig="punc1" postag_orig="u--------" relation_orig="AuxK" head_orig="0" lemma_reg="punc1" postag_reg="u--------" relation_reg="AuxK" head_reg="0" tp_n="1" line_n="25" lang="grc" hand_id="179" tm_word_id=""/>
  </sentence>
  <sentence id="6">
    <word id="1" form_orig="ἐδάνεισεν" form_reg="ἐδάνεισεν" lemma_orig="δανείζω" postag_orig="v3saia---" relation_orig="ExD" head_orig="0" lemma_reg="δανείζω" postag_reg="v3saia---" relation_reg="ExD" head_reg="0" tp_n="2" line_n="1" lang="grc" hand_id="180" tm_word_id=""/>
    <word id="2" form_orig="Ὧρος" form_reg="Ὧρος" lemma_orig="Ὡρος" postag_orig="n-s---mn-" relation_orig="SBJ" head_orig="1" lemma_reg="Ὡρος" postag_reg="n-s---mn-" relation_reg="SBJ" head_reg="1" tp_n="2" line_n="1" lang="grc" hand_id="181" tm_word_id=""/>
    <word id="3" form_orig="Ὥ̣ρ̣ου" form_reg="Ὥρου" lemma_orig="Ὡρος" postag_orig="n-s---mg-" relation_orig="ATR" head_orig="2" lemma_reg="Ὡρος" postag_reg="n-s---mg-" relation_reg="ATR" head_reg="2" tp_n="2" line_n="1" lang="grc" hand_id="182" tm_word_id=""/>
    <word id="4" form_orig="Ὥρωι" form_reg="Ὥρωι" lemma_orig="Ὡρος" postag_orig="n-s---md-" relation_orig="OBJ" head_orig="1" lemma_reg="Ὡρος" postag_reg="n-s---md-" relation_reg="OBJ" head_reg="1" tp_n="2" line_n="1" lang="grc" hand_id="183" tm_word_id=""/>
    <word id="5" form_orig="Νε̣χ̣ούτου" form_reg="Νεχούτου" lemma_orig="Νεχουτης" postag_orig="n-s---mg-" relation_orig="ATR" head_orig="4" lemma_reg="Νεχουτης" postag_reg="n-s---mg-" relation_reg="ATR" head_reg="4" tp_n="2" line_n="1" lang="grc" hand_id="184" tm_word_id=""/>
    <word id="6" form_orig="." form_reg="." lemma_orig="punc1" postag_orig="u--------" relation_orig="AuxK" head_orig="0" lemma_reg="punc1" postag_reg="u--------" relation_reg="AuxK" head_reg="0" tp_n="2" line_n="1" lang="grc" hand_id="185" tm_word_id=""/>
  </sentence>
  <sentence id="4">
    <word id="59" form_orig="[0]" form_reg="[0]" lemma_orig="" postag_orig="" relation_orig="ADV" head_orig="55" lemma_reg="" postag_reg="" relation_reg="ADV" head_reg="55" insertion_id="0055e" artificial="elliptic" tp_n="" line_n="" lang="" hand_id="186" tm_word_id=""/>
  </sentence>
</treebank>
